modules/ALU/ALU_WORD.v
`include "modules/headers/alu_op.vh"

module ALU_WORD (
    input [31:0] src_A,             // source operand A
    input [31:0] src_B,             // source operand B
    input [4:0] alu_op,        		// ALU operation signal (from ALU Control module)
    
    output reg [31:0] alu_result,   // ALU result
    output reg alu_zero             // zero flag
);

    always @(*) begin
        case (alu_op)
            `ALU_OP_ADD: begin
                alu_result = src_A + src_B;
            end

            `ALU_OP_SUB: begin
                alu_result = src_A - src_B;
            end
			
			`ALU_OP_SLL: begin
				alu_result = src_A << src_B;
			end
			
			`ALU_OP_SRL: begin
				alu_result = src_A >> src_B;
			end
			
			`ALU_OP_SRA: begin
				alu_result = $signed(src_A) >>> src_B;
			end
			
			`ALU_OP_NOP: begin
				alu_result = 32'd0;
			end

            default: begin
                alu_result = 32'd0; // Default case: zero result
            end
        endcase

        alu_zero = (alu_result == 32'd0); // Zero flag: set if result is zero
    end

endmodule

testbenches/ALU/ALU_WORD_tb.v
`timescale 1ns/1ps

`include "modules/headers/alu_op.vh"

module ALU_WORD_tb;
    reg [31:0] src_A;
	reg [31:0] src_B;
    reg [4:0] alu_op;

    wire [31:0] alu_result;
    wire alu_zero;

    ALU_WORD dut (
        .src_A(src_A),
        .src_B(src_B),
        .alu_op(alu_op),

        .alu_result(alu_result),
        .alu_zero(alu_zero)
    );

    initial begin
        $dumpfile("testbenches/results/waveforms/ALU_WORD_tb_result.vcd");
        $dumpvars(0, dut);

        // Test sequence
        $display("==================== ALU_WORD Test START ====================");

        // Test 1: Addition
		$display("\nAddition Test: ");
		
        alu_op = `ALU_OP_ADD;

        src_A = 32'd0; src_B = 32'd0; #10;
        $display("%d + %d = %d, Zero: %b", src_A, src_B, alu_result, alu_zero);
		
		src_A = 32'd1000; src_B = 32'd2000; #10;
        $display("%d + %d = %d, Zero: %b", src_A, src_B, alu_result, alu_zero);
		
		src_A = 32'd1972; src_B = 32'd1121; #10;
        $display("%d + %d = %d, Zero: %b", src_A, src_B, alu_result, alu_zero);

        // Test 2: Subtraction
		$display("\nSubtraction Test: ");
		
        alu_op = `ALU_OP_SUB;

        src_A = 32'd30; src_B = 32'd30; #10;
        $display("%d - %d = %d, Zero: %b", src_A, src_B, alu_result, alu_zero);
		
		src_A = 32'd10; src_B = 32'd20; #10;
        $display("%d - %d = %d, Zero: %b", src_A, src_B, $signed(alu_result), alu_zero);
		
		src_A = 32'd1972; src_B = 32'd1121; #10;
        $display("%d - %d = %d, Zero: %b", src_A, src_B, alu_result, alu_zero);

		// Test 3: SLL
		$display("\nShift Left Logic Test: ");
		
        alu_op = `ALU_OP_SLL;

		src_A = 32'h1234_5679; src_B = 32'd31; #10;
        $display("%h << %d = %h, Zero: %b", src_A, src_B, alu_result, alu_zero);
		
        src_A = 32'h0FFF_FFFF; src_B = 32'd3; #10;
        $display("%h << %d = %h, Zero: %b", src_A, src_B, alu_result, alu_zero);
		
		src_A = 32'h0F0F_FF00; src_B = 32'd1972; #10;
        $display("%h << %d = %h, Zero: %b", src_A, src_B, alu_result, alu_zero);
		
		// Test 4: SRL
		$display("\nShift Right Logic Test: ");
		
        alu_op = `ALU_OP_SRL;

        src_A = 32'hFDEA_DBEF; src_B = 32'd4; #10;
        $display("%h >> %d = %h, Zero: %b", src_A, src_B, alu_result, alu_zero);
		
		src_A = 32'hDEAD_BEEF; src_B = 32'd8; #10;
        $display("%h >> %d = %h, Zero: %b", src_A, src_B, alu_result, alu_zero);
		
		src_A = 32'hFFFF_FFFF; src_B = 32'd1972; #10;
        $display("%h >> %d = %h, Zero: %b", src_A, src_B, alu_result, alu_zero);

        // Test 5: SRA
		$display("\nShift Right Arithmetic Test: ");

        alu_op = `ALU_OP_SRA;

        src_A = 32'hFDEA_DBEF; src_B = 32'd4; #10;
        $display("%h >>> %d = %h, Zero: %b", src_A, src_B, alu_result, alu_zero);

        src_A = 32'h8000_0000; src_B = 32'd1972; #10;
        $display("%h >>> %d = %h, Zero: %b", src_A, src_B, alu_result, alu_zero);
		
		src_A = 32'h0000_0000; src_B = 32'd31011; #10;
        $display("%h >>> %d = %h, Zero: %b", src_A, src_B, alu_result, alu_zero);

        // Test 6: NOP
		$display("\nNOP Test: ");
		
        alu_op = `ALU_OP_NOP;

        src_A = 32'hDEAD_BEEF; src_B = 32'hCAFE_BEBE; #10;
        $display("%h NOP %h = %h, Zero: %b", src_A, src_B, alu_result, alu_zero);

        src_A = 32'd1972; src_B = 32'd1121; #10;
        $display("%d NOP %d = %d, Zero: %b", src_A, src_B, alu_result, alu_zero);
		
		src_A = 32'd31011; src_B = 32'd31011; #10;
        $display("%d NOP %d = %d, Zero: %b", src_A, src_B, alu_result, alu_zero);

        $display("\n====================  ALU_WORD Test END  ====================");

        $stop;
    end

endmodule

testbenches/results/waveforms/ALU_WORD_tb_result.vcd
$date
	Sat Jun 28 13:49:56 2025
$end
$version
	Icarus Verilog
$end
$timescale
	1ps
$end
$scope module ALU_WORD_tb $end
$scope module dut $end
$var wire 5 ! alu_op [4:0] $end
$var wire 32 " src_A [31:0] $end
$var wire 32 # src_B [31:0] $end
$var reg 32 $ alu_result [31:0] $end
$var reg 1 % alu_zero $end
$upscope $end
$upscope $end
$enddefinitions $end
$comment Show the parameter values. $end
$dumpall
$end
#0
$dumpvars
1%
b0 $
b0 #
b0 "
b0 !
$end
#10000
0%
b101110111000 $
b11111010000 #
b1111101000 "
#20000
b110000010101 $
b10001100001 #
b11110110100 "
#30000
1%
b0 $
b11110 #
b11110 "
b10 !
#40000
0%
b11111111111111111111111111110110 $
b10100 #
b1010 "
#50000
b1101010011 $
b10001100001 #
b11110110100 "
#60000
b10000000000000000000000000000000 $
b11111 #
b10010001101000101011001111001 "
b1001 !
#70000
b1111111111111111111111111111000 $
b11 #
b1111111111111111111111111111 "
#80000
1%
b0 $
b11110110100 #
b1111000011111111111100000000 "
#90000
0%
b1111110111101010110110111110 $
b100 #
b11111101111010101101101111101111 "
b1011 !
#100000
b110111101010110110111110 $
b1000 #
b11011110101011011011111011101111 "
#110000
1%
b0 $
b11110110100 #
b11111111111111111111111111111111 "
#120000
0%
b11111111110111101010110110111110 $
b100 #
b11111101111010101101101111101111 "
b1101 !
#130000
b11111111111111111111111111111111 $
b11110110100 #
b10000000000000000000000000000000 "
#140000
1%
b0 $
b111100100100011 #
b0 "
#150000
b11001010111111101011111010111110 #
b11011110101011011011111011101111 "
b11111 !
#160000
b10001100001 #
b11110110100 "
#170000
b111100100100011 #
b111100100100011 "
