modules/Branch_Predictor.v
`include "modules/headers/opcode.vh"

module BranchPredictor #(
    parameter XLEN = 64
) (
    input wire clk,
    input wire reset,
    input wire [6:0] IF_opcode,
    input wire [XLEN-1:0] IF_pc,
    input wire [XLEN-1:0] IF_imm,
    input wire EX_branch,
    input wire EX_branch_taken,
    
    output reg branch_estimation,
    output reg [XLEN-1:0] branch_target
);
    reg [1:0] prediction_counter;
    reg branch_prediction;
    wire [XLEN-1:0] prediction_target = branch_estimation ? (IF_pc + IF_imm) : (IF_pc + {{XLEN-3{1'b0}},3'd4});

    always @(*) begin
        if (IF_opcode == `OPCODE_BRANCH) begin
            branch_estimation = prediction_counter[1];
            branch_target = prediction_target;
        end
        else begin
            branch_estimation = 1'b0;
            branch_target = {XLEN{1'b0}};
        end
    end

    always @(posedge clk or posedge reset) begin
        if (reset) begin
            branch_prediction <= 1'b0;
            prediction_counter <= 2'b00;
        end else begin
            if (IF_opcode == `OPCODE_BRANCH) begin
                branch_prediction <= branch_estimation;
            end
        
        if (EX_branch && (EX_branch_taken == 1'b1 || EX_branch_taken == 1'b0)) begin
                case ({EX_branch_taken, prediction_counter})
                // Not Taken 0, prediction_counter 00
                    3'b0_00: prediction_counter <= 2'b00; // Strongly Not Taken <- if not taken again, still 00.
                    3'b0_01: prediction_counter <= 2'b00; // Weakly Not Taken <- if not taken again, 00.
                    3'b0_10: prediction_counter <= 2'b01; // Weakly Taken <- if not taken, 01.
                    3'b0_11: prediction_counter <= 2'b10; // Strongly Taken <- if not taken, 10.
                // Taken 1, prediction_counter 00
                    3'b1_00: prediction_counter <= 2'b01; // Strongly Not Taken <- if taken, 01.
                    3'b1_01: prediction_counter <= 2'b10; // Weakly Not Taken <- if taken, 10.
                    3'b1_10: prediction_counter <= 2'b11; // Weakly Taken <- if taken again, 11.
                    3'b1_11: prediction_counter <= 2'b11; // Strongly Taken <- if taken again, still 11.
            endcase
            end
        end
    end

    
endmodule

testbenches/Branch_Predictor_tb.v
`timescale 1ns/1ps
`include "modules/headers/opcode.vh"

module BranchPredictor_tb #(
    parameter XLEN = 64
);
    reg clk = 0;
    reg reset = 0;

    reg [6:0] IF_opcode;
    reg [XLEN-1:0] IF_pc;
    reg [XLEN-1:0] IF_imm;
    reg EX_branch;
    reg EX_branch_taken;
    
    wire branch_estimation;
    wire [XLEN-1:0] branch_target;

    BranchPredictor #(.XLEN(XLEN)) branch_predictor(
        .clk(clk),
        .reset(reset),
        .IF_opcode(IF_opcode),
        .IF_pc (IF_pc),
        .IF_imm (IF_imm),
        .EX_branch(EX_branch),
        .EX_branch_taken (EX_branch_taken),

        .branch_estimation (branch_estimation),
        .branch_target (branch_target)
    );

    always #5 clk = ~clk;

    initial begin
        $dumpfile("testbenches/results/waveforms/BranchPredictor_tb.vcd");
        $dumpvars(0, branch_predictor);

        // Test sequence
        $display("==================== Branch Predictor Test START ====================");
        $display("");

        // reset
        reset = 1'b1;
        #30;
        reset = 1'b0;
        $display("[RESET] Branch Predictor Reset Complete");
        $display("        Initial prediction_counter = %b (Strongly Not Taken)", branch_predictor.prediction_counter);
        $display("");

        IF_opcode = 7'b0;
        IF_pc = {XLEN{1'b0}};
        IF_imm = {XLEN{1'b0}};
        EX_branch = 1'b0;
        EX_branch_taken = 1'bx;
        // ---------------------------------------------------------------
        // Test 1: Prediction = NT, Actual = Taken (misprediction)
        $display("---------------------------------------------------------------");
        $display("[TEST 1] Prediction = NT, Actual = Taken (misprediction expected)");
        @(negedge clk);
        IF_opcode = `OPCODE_BRANCH;
        IF_pc = 64'h0000_0000;
        IF_imm = 64'd8;
        repeat (2) @(negedge clk);

        $display("        IF_pc = 0x%h, IF_imm = %0d", IF_pc, IF_imm);
        $display("        branch_estimation = %b (0=NT, 1=T)", branch_estimation);
        $display("        branch_target = 0x%h", branch_target);

        // misprediction, prediction counter is now Weakly Not Taken.
        EX_branch_taken = 1'b1;
        EX_branch = 1'b1;
        #10;
        $display("        EX_branch_taken = %b (Actual: Taken)", EX_branch_taken);
        $display("        prediction_counter after update = %b (Expected: 01 Weakly NT)", branch_predictor.prediction_counter);
        $display("        Result: %s", (branch_predictor.prediction_counter == 2'b01) ? "PASS" : "FAIL");
        $display("");
        // ---------------------------------------------------------------
        // Test 2: Prediction = NT, Actual = Not Taken (well predicted)
        $display("---------------------------------------------------------------");
        $display("[TEST 2] Prediction = NT, Actual = Not Taken (correct prediction)");
        @(negedge clk);
        IF_pc = 64'h0000_0000_0000_0008;
        IF_imm = 64'd12;
        EX_branch = 1'b0;
        repeat (2) @(negedge clk);

        $display("        IF_pc = 0x%h, IF_imm = %0d", IF_pc, IF_imm);
        $display("        branch_estimation = %b (0=NT, 1=T)", branch_estimation);
        $display("        branch_target = 0x%h", branch_target);

        // well predicted, prediction counter is now Strongly Not Taken.
        EX_branch = 1'b1;
        EX_branch_taken = 1'b0; // Target address = 0x0000_000C (PC+4)
        #10;
        $display("        EX_branch_taken = %b (Actual: Not Taken)", EX_branch_taken);
        $display("        prediction_counter after update = %b (Expected: 00 Strongly NT)", branch_predictor.prediction_counter);
        $display("        Result: %s", (branch_predictor.prediction_counter == 2'b00) ? "PASS" : "FAIL");
        $display("");
        // ---------------------------------------------------------------
        // Test 3: Prediction = NT, Actual = Taken (misprediction)
        $display("---------------------------------------------------------------");
        $display("[TEST 3] Prediction = NT, Actual = Taken (misprediction expected)");
        @(negedge clk);
        IF_pc = 64'h0000_0000_0000_000C;
        IF_imm = 64'd8;
        EX_branch = 1'b0;
        repeat (2) @(negedge clk);

        $display("        IF_pc = 0x%h, IF_imm = %0d", IF_pc, IF_imm);
        $display("        branch_estimation = %b (0=NT, 1=T)", branch_estimation);
        $display("        branch_target = 0x%h", branch_target);

        // misprediction, prediction counter is now Weakly Not Taken.
        EX_branch = 1'b1;
        EX_branch_taken = 1'b1; 
        #10;
        $display("        EX_branch_taken = %b (Actual: Taken)", EX_branch_taken);
        $display("        prediction_counter after update = %b (Expected: 01 Weakly NT)", branch_predictor.prediction_counter);
        $display("        Result: %s", (branch_predictor.prediction_counter == 2'b01) ? "PASS" : "FAIL");
        $display("");
        // ---------------------------------------------------------------
        // Test 4: Prediction = NT, Actual = Taken (mispredicted)
        $display("---------------------------------------------------------------");
        $display("[TEST 4] Prediction = NT, Actual = Taken (misprediction expected)");
        @(negedge clk);
        IF_pc = 64'h0000_0000_0000_0014;
        IF_imm = 64'd12;
        EX_branch = 1'b0;
        repeat (2) @(negedge clk);

        $display("        IF_pc = 0x%h, IF_imm = %0d", IF_pc, IF_imm);
        $display("        branch_estimation = %b (0=NT, 1=T)", branch_estimation);
        $display("        branch_target = 0x%h", branch_target);

        // mispredicted, prediction counter is now Weakly Taken.
        EX_branch = 1'b1;
        EX_branch_taken = 1'b1; // Target address = 0x0000_0020
        #10;
        $display("        EX_branch_taken = %b (Actual: Taken)", EX_branch_taken);
        $display("        prediction_counter after update = %b (Expected: 10 Weakly T)", branch_predictor.prediction_counter);
        $display("        Result: %s", (branch_predictor.prediction_counter == 2'b10) ? "PASS" : "FAIL");
        $display("");
        // ---------------------------------------------------------------
        // Test 5: Prediction = T, Actual = Taken (well predicted)
        $display("---------------------------------------------------------------");
        $display("[TEST 5] Prediction = T, Actual = Taken (correct prediction)");
        @(negedge clk);
        IF_pc = 64'h0000_0000_0000_0020;
        IF_imm = 64'd8;
        EX_branch = 1'b0;
        repeat (2) @(negedge clk);

        $display("        IF_pc = 0x%h, IF_imm = %0d", IF_pc, IF_imm);
        $display("        branch_estimation = %b (0=NT, 1=T)", branch_estimation);
        $display("        branch_target = 0x%h", branch_target);

        // well predicted, prediction counter is now Strongly Taken.
        EX_branch = 1'b1;
        EX_branch_taken = 1'b1; // Target address = 0x0000_0028
        #10;
        $display("        EX_branch_taken = %b (Actual: Taken)", EX_branch_taken);
        $display("        prediction_counter after update = %b (Expected: 11 Strongly T)", branch_predictor.prediction_counter);
        $display("        Result: %s", (branch_predictor.prediction_counter == 2'b11) ? "PASS" : "FAIL");
        $display("");
        // ---------------------------------------------------------------
        $display("==================== Branch Predictor Test FINISH ====================");
        #40;
        $finish;
    end
endmodule

testbenches/results/waveforms/BranchPredictor_tb.vcd
$date
	Sun Dec 28 15:56:42 2025
$end
$version
	Icarus Verilog
$end
$timescale
	1ps
$end
$scope module BranchPredictor_tb $end
$scope module branch_predictor $end
$var wire 1 ! EX_branch $end
$var wire 1 " EX_branch_taken $end
$var wire 64 # IF_imm [63:0] $end
$var wire 7 $ IF_opcode [6:0] $end
$var wire 64 % IF_pc [63:0] $end
$var wire 1 & clk $end
$var wire 1 ' reset $end
$var wire 64 ( prediction_target [63:0] $end
$var parameter 32 ) XLEN $end
$var reg 1 * branch_estimation $end
$var reg 1 + branch_prediction $end
$var reg 64 , branch_target [63:0] $end
$var reg 2 - prediction_counter [1:0] $end
$upscope $end
$upscope $end
$enddefinitions $end
$comment Show the parameter values. $end
$dumpall
b1000000 )
$end
#0
$dumpvars
b0 -
b0 ,
0+
0*
bx (
1'
0&
bx %
bx $
bx #
x"
x!
$end
#5000
1&
#10000
0&
#15000
1&
#20000
0&
#25000
1&
#30000
b100 ,
b100 (
0&
0!
b1000 #
b0 %
b1100011 $
0'
#35000
1&
#40000
0&
#45000
1&
#50000
1!
1"
0&
#55000
b1 -
1&
#60000
b1100 ,
b1100 (
0!
b1100 #
b1000 %
0&
#65000
1&
#70000
0&
#75000
1&
#80000
0"
1!
0&
#85000
b0 -
1&
#90000
b10000 ,
b10000 (
0!
b1000 #
b1100 %
0&
#95000
1&
#100000
0&
#105000
1&
#110000
1"
1!
0&
#115000
b1 -
1&
#120000
b11000 ,
b11000 (
0!
b1100 #
b10100 %
0&
#125000
1&
#130000
0&
#135000
1&
#140000
1!
0&
#145000
b100000 ,
b100000 (
1*
b10 -
1&
#150000
b101000 ,
b101000 (
0!
b1000 #
b100000 %
0&
#155000
1+
1&
#160000
0&
#165000
1&
#170000
1!
0&
#175000
b11 -
1&
