modules/Byte_Enable_Logic.v
`include "modules/headers/load_funct3.vh"
`include "modules/headers/store_funct3.vh"

module ByteEnableLogic #(
	parameter XLEN = 64
)(
    input memory_read,							// signal indicating that register file should read from data memory
    input memory_write,							// signal indicating that register file should write to data memory
    input [2:0] funct3,							// funct3
	input [XLEN-1:0] register_file_read_data,		// data read from register file
	input [XLEN-1:0] data_memory_read_data,			// data read from data memory
	input [XLEN-1:0] address,						// address for checking alignment
	
	output reg [XLEN-1:0] register_file_write_data,	// data to write at register file
	output reg [XLEN-1:0] data_memory_write_data,	// data to write at data memory
    output reg [7:0] write_mask					// bitmask for writing data
);

    always @(*) begin
        if (memory_read) begin
			data_memory_write_data = {XLEN{1'b0}};
			write_mask = 8'b0;
			
			case (funct3)
				`LOAD_LB: begin
					register_file_write_data = {{(XLEN-8){data_memory_read_data[7]}}, data_memory_read_data[7:0]};
				end
				`LOAD_LH: begin
					register_file_write_data = {{(XLEN-16){data_memory_read_data[15]}}, data_memory_read_data[15:0]};
				end
				`LOAD_LW: begin
					register_file_write_data = {{(XLEN-32){data_memory_read_data[31]}}, data_memory_read_data[31:0]};
				end
                `LOAD_LD: begin
					register_file_write_data = data_memory_read_data;
                end
				`LOAD_LBU: begin
					register_file_write_data = {{(XLEN-8){1'b0}}, data_memory_read_data[7:0]};
				end
				`LOAD_LHU: begin
					register_file_write_data = {{(XLEN-16){1'b0}}, data_memory_read_data[15:0]};
				end
                `LOAD_LWU: begin
					register_file_write_data = {{(XLEN-32){1'b0}}, data_memory_read_data[31:0]};
                end
				default: begin
					register_file_write_data = {XLEN{1'b0}};
				end
			endcase
		end
		else if (memory_write) begin
			register_file_write_data = {XLEN{1'b0}};
						
			case (funct3)
				`STORE_SB: begin
					data_memory_write_data = {8{register_file_read_data[7:0]}};
					
					case (address[2:0])
						3'b000: begin
							write_mask = 8'b0000_0001;
						end
						3'b001: begin
							write_mask = 8'b0000_0010;
						end
						3'b010: begin
							write_mask = 8'b0000_0100;
						end
						3'b011: begin
							write_mask = 8'b0000_1000;
						end
						3'b100: begin
							write_mask = 8'b0001_0000;
						end
						3'b101: begin
							write_mask = 8'b0010_0000;
						end
						3'b110: begin
							write_mask = 8'b0100_0000;
						end
						3'b111: begin
							write_mask = 8'b1000_0000;
						end
					endcase
				end
				`STORE_SH: begin
					data_memory_write_data = {4{register_file_read_data[15:0]}};
					
					case (address[2:0])
						3'b000: begin
							write_mask = 8'b0000_0011;
						end
						3'b010: begin
							write_mask = 8'b0000_1100;
						end
						3'b100: begin
							write_mask = 8'b0011_0000;
						end
						3'b110: begin
							write_mask = 8'b1100_0000;
						end
						default: begin
							write_mask = 8'b0;
						end
					endcase
				end
				`STORE_SW: begin
					data_memory_write_data = {2{register_file_read_data[31:0]}};
					
					case (address[2:0])
						3'b000: begin
							write_mask = 8'b0000_1111;
						end
						3'b100: begin
							write_mask = 8'b1111_0000;
						end
						default: begin
							write_mask = 8'b0;
						end
					endcase
				end
				`STORE_SD: begin
					data_memory_write_data = register_file_read_data;

					if (address[2:0] == 3'b0) begin
						write_mask = 8'b1111_1111;
					end
					else begin
						write_mask = 8'b0;
					end
				end
				default: begin
					data_memory_write_data = {XLEN{1'b0}};
					write_mask = 8'b0;
				end
			endcase
		end
		else begin
			register_file_write_data = {XLEN{1'b0}};
			data_memory_write_data = {XLEN{1'b0}};
			write_mask = 8'b0;
		end
    end

endmodule

testbenches/Byte_Enable_Logic_tb.v
`timescale 1ns/1ps

`include "modules/headers/load_funct3.vh"
`include "modules/headers/store_funct3.vh"

module ByteEnableLogic_tb;
	reg memory_read;
    reg memory_write;
    reg [2:0] funct3;
	reg [63:0] register_file_read_data;
	reg [63:0] data_memory_read_data;
	reg [2:0] address;
	
	reg [63:0] original_data;
	
	wire [63:0] register_file_write_data;
	wire [63:0] data_memory_write_data;
    wire [7:0] write_mask;

    ByteEnableLogic dut (
        .memory_read(memory_read),
		.memory_write(memory_write),
		.funct3(funct3),
		.register_file_read_data(register_file_read_data),
		.data_memory_read_data(data_memory_read_data),
		.address(address),

		.register_file_write_data(register_file_write_data),
		.data_memory_write_data(data_memory_write_data),
		.write_mask(write_mask)
    );

    initial begin
        $dumpfile("testbenches/results/waveforms/Byte_Enable_Logic_tb_result.vcd");
        $dumpvars(0, dut);

        // Test sequence
        $display("==================== Byte Enable Logic Test START ====================");

        memory_read = 0;
		memory_write = 0;
		funct3 = 3'b0;
		register_file_read_data = 64'b0;
		data_memory_read_data = 64'b0;
		address = 64'b0;
		
        // Test 1: Load
		$display("\nLoad: \n");
		
		data_memory_read_data = 64'hDEAD_BEEF_CAFE_BABE;
		
		#10;
		$display("Full data to load: %h, Actual data loaded: %h (load disabled)", data_memory_read_data, register_file_write_data);
		
		memory_read = 1;
		
		funct3 = `LOAD_LB; #10;
        $display("Full data to load: %h, Actual data loaded: %h, funct3: %b, address: %h", data_memory_read_data, register_file_write_data, funct3, address);
		
		funct3 = `LOAD_LH; #10;
        $display("Full data to load: %h, Actual data loaded: %h, funct3: %b, address: %h", data_memory_read_data, register_file_write_data, funct3, address);
		
		funct3 = `LOAD_LW; #10;
        $display("Full data to load: %h, Actual data loaded: %h, funct3: %b, address: %h", data_memory_read_data, register_file_write_data, funct3, address);

        funct3 = `LOAD_LD; #10;
        $display("Full data to load: %h, Actual data loaded: %h, funct3: %b, address: %h", data_memory_read_data, register_file_write_data, funct3, address);
		
		funct3 = `LOAD_LBU; #10;
        $display("Full data to load: %h, Actual data loaded: %h, funct3: %b, address: %h", data_memory_read_data, register_file_write_data, funct3, address);
		
		funct3 = `LOAD_LHU; #10;
        $display("Full data to load: %h, Actual data loaded: %h, funct3: %b, address: %h", data_memory_read_data, register_file_write_data, funct3, address);

        funct3 = `LOAD_LWU; #10;
        $display("Full data to load: %h, Actual data loaded: %h, funct3: %b, address: %h", data_memory_read_data, register_file_write_data, funct3, address);
		
		// Test 2: Store
		$display("\nStore: ");
		
		original_data = 64'hCCCC_CCCC_CCCC_CCCC;
		
		memory_read = 0;
		funct3 = 3'b0;
		data_memory_read_data = 64'b0;
		address = 64'h0000_0000_0000_00F0;
		
		register_file_read_data = 64'hCAFE_BABE_DEAD_BEEF;
		
		#10;
		$display("%h (register) -> %h (duplicated), store disabled, address: %h, write_mask: %b\n", register_file_read_data, data_memory_write_data, address, write_mask);
		
		memory_write = 1;
		
		funct3 = `STORE_SB;
		
		address = 64'hF0; #10;
		$display("%h (register) -> %h (duplicated), funct3: %b, address: %h, write_mask: %b", register_file_read_data, data_memory_write_data, funct3, address, write_mask);
		
		address = 64'hF1; #10;
		$display("%h (register) -> %h (duplicated), funct3: %b, address: %h, write_mask: %b", register_file_read_data, data_memory_write_data, funct3, address, write_mask);
		
		address = 64'hF2; #10;
		$display("%h (register) -> %h (duplicated), funct3: %b, address: %h, write_mask: %b", register_file_read_data, data_memory_write_data, funct3, address, write_mask);
		
		address = 64'hF3; #10;
		$display("%h (register) -> %h (duplicated), funct3: %b, address: %h, write_mask: %b", register_file_read_data, data_memory_write_data, funct3, address, write_mask);
		
		address = 64'hF4; #10;
		$display("%h (register) -> %h (duplicated), funct3: %b, address: %h, write_mask: %b", register_file_read_data, data_memory_write_data, funct3, address, write_mask);

        address = 64'hF5; #10;
		$display("%h (register) -> %h (duplicated), funct3: %b, address: %h, write_mask: %b", register_file_read_data, data_memory_write_data, funct3, address, write_mask);

        address = 64'hF6; #10;
		$display("%h (register) -> %h (duplicated), funct3: %b, address: %h, write_mask: %b", register_file_read_data, data_memory_write_data, funct3, address, write_mask);
		
        address = 64'hF7; #10;
		$display("%h (register) -> %h (duplicated), funct3: %b, address: %h, write_mask: %b\n", register_file_read_data, data_memory_write_data, funct3, address, write_mask);

		funct3 = `STORE_SH;
		
		address = 64'hF0; #10;
		$display("%h (register) -> %h (duplicated), funct3: %b, address: %h, write_mask: %b", register_file_read_data, data_memory_write_data, funct3, address, write_mask);
		
		address = 64'hF1; #10;
		$display("%h (register) -> %h (duplicated), funct3: %b, address: %h, write_mask: %b", register_file_read_data, data_memory_write_data, funct3, address, write_mask);
		
		address = 64'hF2; #10;
		$display("%h (register) -> %h (duplicated), funct3: %b, address: %h, write_mask: %b", register_file_read_data, data_memory_write_data, funct3, address, write_mask);
		
		address = 64'hF3; #10;
		$display("%h (register) -> %h (duplicated), funct3: %b, address: %h, write_mask: %b", register_file_read_data, data_memory_write_data, funct3, address, write_mask);
		
		address = 64'hF4; #10;
		$display("%h (register) -> %h (duplicated), funct3: %b, address: %h, write_mask: %b", register_file_read_data, data_memory_write_data, funct3, address, write_mask);

        address = 64'hF5; #10;
		$display("%h (register) -> %h (duplicated), funct3: %b, address: %h, write_mask: %b", register_file_read_data, data_memory_write_data, funct3, address, write_mask);

        address = 64'hF6; #10;
		$display("%h (register) -> %h (duplicated), funct3: %b, address: %h, write_mask: %b", register_file_read_data, data_memory_write_data, funct3, address, write_mask);
		
        address = 64'hF7; #10;
		$display("%h (register) -> %h (duplicated), funct3: %b, address: %h, write_mask: %b\n", register_file_read_data, data_memory_write_data, funct3, address, write_mask);

		funct3 = `STORE_SW; 
		
		address = 64'hF0; #10;
		$display("%h (register) -> %h (duplicated), funct3: %b, address: %h, write_mask: %b", register_file_read_data, data_memory_write_data, funct3, address, write_mask);
		
		address = 64'hF1; #10;
		$display("%h (register) -> %h (duplicated), funct3: %b, address: %h, write_mask: %b", register_file_read_data, data_memory_write_data, funct3, address, write_mask);
		
		address = 64'hF2; #10;
		$display("%h (register) -> %h (duplicated), funct3: %b, address: %h, write_mask: %b", register_file_read_data, data_memory_write_data, funct3, address, write_mask);
		
		address = 64'hF3; #10;
		$display("%h (register) -> %h (duplicated), funct3: %b, address: %h, write_mask: %b", register_file_read_data, data_memory_write_data, funct3, address, write_mask);
		
		address = 64'hF4; #10;
		$display("%h (register) -> %h (duplicated), funct3: %b, address: %h, write_mask: %b", register_file_read_data, data_memory_write_data, funct3, address, write_mask);

        address = 64'hF5; #10;
		$display("%h (register) -> %h (duplicated), funct3: %b, address: %h, write_mask: %b", register_file_read_data, data_memory_write_data, funct3, address, write_mask);

        address = 64'hF6; #10;
		$display("%h (register) -> %h (duplicated), funct3: %b, address: %h, write_mask: %b", register_file_read_data, data_memory_write_data, funct3, address, write_mask);
		
        address = 64'hF7; #10;
		$display("%h (register) -> %h (duplicated), funct3: %b, address: %h, write_mask: %b\n", register_file_read_data, data_memory_write_data, funct3, address, write_mask);
		
        funct3 = `STORE_SD; 
		
		address = 64'hF0; #10;
		$display("%h (register) -> %h (duplicated), funct3: %b, address: %h, write_mask: %b", register_file_read_data, data_memory_write_data, funct3, address, write_mask);
		
		address = 64'hF1; #10;
		$display("%h (register) -> %h (duplicated), funct3: %b, address: %h, write_mask: %b", register_file_read_data, data_memory_write_data, funct3, address, write_mask);
		
		address = 64'hF2; #10;
		$display("%h (register) -> %h (duplicated), funct3: %b, address: %h, write_mask: %b", register_file_read_data, data_memory_write_data, funct3, address, write_mask);
		
		address = 64'hF3; #10;
		$display("%h (register) -> %h (duplicated), funct3: %b, address: %h, write_mask: %b", register_file_read_data, data_memory_write_data, funct3, address, write_mask);
		
		address = 64'hF4; #10;
		$display("%h (register) -> %h (duplicated), funct3: %b, address: %h, write_mask: %b", register_file_read_data, data_memory_write_data, funct3, address, write_mask);

        address = 64'hF5; #10;
		$display("%h (register) -> %h (duplicated), funct3: %b, address: %h, write_mask: %b", register_file_read_data, data_memory_write_data, funct3, address, write_mask);

        address = 64'hF6; #10;
		$display("%h (register) -> %h (duplicated), funct3: %b, address: %h, write_mask: %b", register_file_read_data, data_memory_write_data, funct3, address, write_mask);
		
        address = 64'hF7; #10;
		$display("%h (register) -> %h (duplicated), funct3: %b, address: %h, write_mask: %b", register_file_read_data, data_memory_write_data, funct3, address, write_mask);

		$display("\n====================  Byte Enable Logic Test END  ====================");
		
		$stop;
    end

endmodule

testbenches/results/waveforms/Byte_Enable_Logic_tb_result.vcd
$date
	Thu Jul 10 14:19:15 2025
$end
$version
	Icarus Verilog
$end
$timescale
	1ps
$end
$scope module ByteEnableLogic_tb $end
$scope module dut $end
$var wire 64 ! address [63:0] $end
$var wire 64 " data_memory_read_data [63:0] $end
$var wire 3 # funct3 [2:0] $end
$var wire 1 $ memory_read $end
$var wire 1 % memory_write $end
$var wire 64 & register_file_read_data [63:0] $end
$var reg 64 ' data_memory_write_data [63:0] $end
$var reg 64 ( register_file_write_data [63:0] $end
$var reg 8 ) write_mask [7:0] $end
$upscope $end
$upscope $end
$enddefinitions $end
$comment Show the parameter values. $end
$dumpall
$end
#0
$dumpvars
b0 )
b0 (
b0 '
b0 &
0%
0$
b0 #
b1101111010101101101111101110111111001010111111101011101010111110 "
b0 !
$end
#10000
b1111111111111111111111111111111111111111111111111111111110111110 (
1$
#20000
b1111111111111111111111111111111111111111111111111011101010111110 (
b1 #
#30000
b1111111111111111111111111111111111001010111111101011101010111110 (
b10 #
#40000
b1101111010101101101111101110111111001010111111101011101010111110 (
b11 #
#50000
b10111110 (
b100 #
#60000
b1011101010111110 (
b101 #
#70000
b11001010111111101011101010111110 (
b110 #
#80000
b0 (
b1100101011111110101110101011111011011110101011011011111011101111 &
b11110000 !
b0 "
b0 #
0$
#90000
b1 )
b1110111111101111111011111110111111101111111011111110111111101111 '
1%
#100000
b10 )
b11110001 !
#110000
b100 )
b11110010 !
#120000
b1000 )
b11110011 !
#130000
b10000 )
b11110100 !
#140000
b100000 )
b11110101 !
#150000
b1000000 )
b11110110 !
#160000
b10000000 )
b11110111 !
#170000
b11 )
b1011111011101111101111101110111110111110111011111011111011101111 '
b11110000 !
b1 #
#180000
b0 )
b11110001 !
#190000
b1100 )
b11110010 !
#200000
b0 )
b11110011 !
#210000
b110000 )
b11110100 !
#220000
b0 )
b11110101 !
#230000
b11000000 )
b11110110 !
#240000
b0 )
b11110111 !
#250000
b1111 )
b1101111010101101101111101110111111011110101011011011111011101111 '
b11110000 !
b10 #
#260000
b0 )
b11110001 !
#270000
b11110010 !
#280000
b11110011 !
#290000
b11110000 )
b11110100 !
#300000
b0 )
b11110101 !
#310000
b11110110 !
#320000
b11110111 !
#330000
b11111111 )
b1100101011111110101110101011111011011110101011011011111011101111 '
b11110000 !
b11 #
#340000
b0 )
b11110001 !
#350000
b11110010 !
#360000
b11110011 !
#370000
b11110100 !
#380000
b11110101 !
#390000
b11110110 !
#400000
b11110111 !
