modules/Data_Memory.v
module DataMemory #(
    parameter XLEN = 64
)(
    input clk,
    input write_enable,
    input [XLEN-1:0] address,
    input [XLEN-1:0] write_data,
    input [7:0] write_mask,
    input [XLEN-1:0] rom_read_data,
    output [XLEN-1:0] rom_address,
    output reg [XLEN-1:0] read_data
);

    reg [XLEN-1:0] memory [0:1023];
    reg [XLEN-1:0] new_word;
    wire [XLEN-1:0] extended_mask = {{8{write_mask[7]}}, {8{write_mask[6]}}, {8{write_mask[5]}}, {8{write_mask[4]}}, {8{write_mask[3]}}, {8{write_mask[2]}}, {8{write_mask[1]}}, {8{write_mask[0]}}};
    wire ram_access = (address[31:16] == 16'h1000);
    wire rom_access = (address[31:16] == 16'h0000);
    wire [12:0] ram_address = address[14:2];
    
    assign rom_address = address;

    integer i;
    initial begin
        for (i=0; i<1024; i=i+1) begin
            memory[i] = {XLEN{1'b0}};
        end
        new_word = {XLEN{1'b0}};
    end

    always @(*) begin
        if (ram_access) begin
            read_data = memory[ram_address];
        end 
        else if (rom_access) begin
            read_data = rom_read_data;
        end 
        else begin
            read_data = {XLEN{1'b0}};
        end
        
    end

    always @(posedge clk) begin
        if (write_enable && ram_access) begin
            new_word = ((memory[ram_address] & ~extended_mask) | (write_data & extended_mask));
            memory[ram_address] <= new_word;
        end
    end

endmodule

testbenches/Data_Memory_tb.v
`timescale 1ns/1ps

module DataMemory_tb;

    parameter XLEN = 64;

    reg clk;
    reg write_enable;
    reg [XLEN-1:0] address;
    reg [XLEN-1:0] write_data;
    reg [7:0] write_mask;
    reg [XLEN-1:0] rom_read_data;

    wire [XLEN-1:0] read_data;
    wire [XLEN-1:0] rom_address;

    // Test result counters
    integer pass_count;
    integer fail_count;
    integer test_num;

    DataMemory #(.XLEN(XLEN)) data_memory (
        .clk(clk),
        .write_enable(write_enable),
        .address(address),
        .write_data(write_data),
        .write_mask(write_mask),
        .rom_read_data(rom_read_data),
        .rom_address(rom_address),
        .read_data(read_data)
    );

    // Generate clock signal (period = 10ns)
    always #5 clk = ~clk;

    // Task for checking results with PASS/FAIL indication
    task check_result;
        input [XLEN-1:0] expected_val;
        input [255:0] test_name;
        begin
            test_num = test_num + 1;
            if (read_data === expected_val) begin
                $display("  [PASS] #%0d %s", test_num, test_name);
                $display("         Expected: %016h | Actual: %016h", expected_val, read_data);
                pass_count = pass_count + 1;
            end else begin
                $display("  [FAIL] #%0d %s", test_num, test_name);
                $display("         Expected: %016h | Actual: %016h", expected_val, read_data);
                fail_count = fail_count + 1;
            end
        end
    endtask

    // Task for checking rom_address
    task check_rom_address;
        input [XLEN-1:0] expected_addr;
        input [255:0] test_name;
        begin
            test_num = test_num + 1;
            if (rom_address === expected_addr) begin
                $display("  [PASS] #%0d %s", test_num, test_name);
                $display("         Expected: %016h | Actual: %016h", expected_addr, rom_address);
                pass_count = pass_count + 1;
            end else begin
                $display("  [FAIL] #%0d %s", test_num, test_name);
                $display("         Expected: %016h | Actual: %016h", expected_addr, rom_address);
                fail_count = fail_count + 1;
            end
        end
    endtask

    initial begin
        $dumpfile("testbenches/results/waveforms/Data_Memory_tb_result.vcd");
        $dumpvars(0, data_memory);

        $display("==================== Data Memory Test START (RV64I) ====================");

        // Initialize signals
        clk = 0;
        write_enable = 0;
        address = 64'h0000_0000_0000_0000;
        write_data = 64'h0000_0000_0000_0000;
        write_mask = 8'b0000_0000;
        rom_read_data = 64'h0000_0000_0000_0000;
        pass_count = 0;
        fail_count = 0;
        test_num = 0;

        #10;

        // ========================================================================
        // Test 1: ROM Address Region Test (0x0000xxxx)
        $display("\n[Test 1] ROM Address Region Read (0x0000xxxx):");
        
        address = 64'h0000_0000_0000_0004;
        rom_read_data = 64'h1234_5678_9ABC_DEF0;
        #10;
        check_result(64'h1234_5678_9ABC_DEF0, "ROM read at 0x00000004");
        check_rom_address(64'h0000_0000_0000_0004, "ROM address output");
        
        address = 64'h0000_0000_0000_1000;
        rom_read_data = 64'hABCD_EF01_2345_6789;
        #10;
        check_result(64'hABCD_EF01_2345_6789, "ROM read at 0x00001000");
        
        address = 64'h0000_0000_0000_FFFC;
        rom_read_data = 64'hCAFE_BABE_DEAD_BEEF;
        #10;
        check_result(64'hCAFE_BABE_DEAD_BEEF, "ROM read at 0x0000FFFC");

        // ========================================================================
        // Test 2: RAM Address Region Initialization (0x1000xxxx)
        $display("\n[Test 2] RAM Address Region Initialization (0x1000xxxx):");

        address = 64'h0000_0000_1000_0004;
        rom_read_data = 64'hDEAD_BEEF_CAFE_BABE;
        #10;
        check_result(64'h0000_0000_0000_0000, "RAM initial value (should be 0)");
        
        // ========================================================================
        // Test 3: RAM Full Write and Read (64-bit)
        $display("\n[Test 3] RAM Full Write and Read (mask=11111111):");

        address = 64'h0000_0000_1000_0004;
        write_data = 64'hDEAD_BEEF_CAFE_BABE;
        write_mask = 8'b1111_1111;
        write_enable = 1;
        rom_read_data = 64'h1234_5678_9ABC_DEF0;
        #10;
        write_enable = 0;
        #10;
        check_result(64'hDEAD_BEEF_CAFE_BABE, "Full 64-bit write");

        // ========================================================================
        // Test 4: RAM Partial Write - Lower 4 Bytes (Byte Masking)
        $display("\n[Test 4] RAM Partial Write - Lower 4 Bytes:");

        // Reset the memory location
        address = 64'h0000_0000_1000_0008;
        write_data = 64'hFFFF_FFFF_FFFF_FFFF;
        write_mask = 8'b1111_1111;
        write_enable = 1;
        #10;
        write_enable = 0;
        #10;

        // mask = 00000001: byte[7:0]
        write_data = 64'h1122_3344_5566_77AA;
        write_mask = 8'b0000_0001;
        write_enable = 1;
        #10;
        write_enable = 0;
        #10;
        check_result(64'hFFFF_FFFF_FFFF_FFAA, "mask=00000001 byte[7:0]");

        // mask = 00000010: byte[15:8]
        write_data = 64'h1122_3344_5566_BB88;
        write_mask = 8'b0000_0010;
        write_enable = 1;
        #10;
        write_enable = 0;
        #10;
        check_result(64'hFFFF_FFFF_FFFF_BBAA, "mask=00000010 byte[15:8]");

        // mask = 00000100: byte[23:16]
        write_data = 64'h1122_3344_55CC_7788;
        write_mask = 8'b0000_0100;
        write_enable = 1;
        #10;
        write_enable = 0;
        #10;
        check_result(64'hFFFF_FFFF_FFCC_BBAA, "mask=00000100 byte[23:16]");

        // mask = 00001000: byte[31:24]
        write_data = 64'h1122_3344_DD66_7788;
        write_mask = 8'b0000_1000;
        write_enable = 1;
        #10;
        write_enable = 0;
        #10;
        check_result(64'hFFFF_FFFF_DDCC_BBAA, "mask=00001000 byte[31:24]");

        // ========================================================================
        // Test 5: RAM Partial Write - Upper 4 Bytes (Byte Masking)
        $display("\n[Test 5] RAM Partial Write - Upper 4 Bytes:");

        // mask = 00010000: byte[39:32]
        write_data = 64'h1122_33EE_5566_7788;
        write_mask = 8'b0001_0000;
        write_enable = 1;
        #10;
        write_enable = 0;
        #10;
        check_result(64'hFFFF_FFEE_DDCC_BBAA, "mask=00010000 byte[39:32]");

        // mask = 00100000: byte[47:40]
        write_data = 64'h1122_FF44_5566_7788;
        write_mask = 8'b0010_0000;
        write_enable = 1;
        #10;
        write_enable = 0;
        #10;
        check_result(64'hFFFF_FFEE_DDCC_BBAA, "mask=00100000 byte[47:40]");

        // mask = 01000000: byte[55:48]
        write_data = 64'h11AB_3344_5566_7788;
        write_mask = 8'b0100_0000;
        write_enable = 1;
        #10;
        write_enable = 0;
        #10;
        check_result(64'hFFAB_FFEE_DDCC_BBAA, "mask=01000000 byte[55:48]");

        // mask = 10000000: byte[63:56]
        write_data = 64'hCD22_3344_5566_7788;
        write_mask = 8'b1000_0000;
        write_enable = 1;
        #10;
        write_enable = 0;
        #10;
        check_result(64'hCDAB_FFEE_DDCC_BBAA, "mask=10000000 byte[63:56]");

        // ========================================================================
        // Test 6: RAM Partial Write - Half-Word and Word Masking
        $display("\n[Test 6] RAM Partial Write - Half-Word and Word:");

        // Reset memory
        address = 64'h0000_0000_1000_000C;
        write_data = 64'h0000_0000_0000_0000;
        write_mask = 8'b1111_1111;
        write_enable = 1;
        #10;
        write_enable = 0;
        #10;

        // mask = 00000011: lower half-word
        write_data = 64'hAAAA_BBBB_CCCC_DDDD;
        write_mask = 8'b0000_0011;
        write_enable = 1;
        #10;
        write_enable = 0;
        #10;
        check_result(64'h0000_0000_0000_DDDD, "mask=00000011 lower half-word");

        // mask = 00001100: second half-word
        write_data = 64'hAAAA_BBBB_EEEE_FFFF;
        write_mask = 8'b0000_1100;
        write_enable = 1;
        #10;
        write_enable = 0;
        #10;
        check_result(64'h0000_0000_EEEE_DDDD, "mask=00001100 second half-word");

        // mask = 00001111: lower word
        address = 64'h0000_0000_1000_0010;
        write_data = 64'h1111_2222_3333_4444;
        write_mask = 8'b0000_1111;
        write_enable = 1;
        #10;
        write_enable = 0;
        #10;
        check_result(64'h0000_0000_3333_4444, "mask=00001111 lower word");

        // mask = 11110000: upper word
        write_data = 64'h5555_6666_7777_8888;
        write_mask = 8'b1111_0000;
        write_enable = 1;
        #10;
        write_enable = 0;
        #10;
        check_result(64'h5555_6666_3333_4444, "mask=11110000 upper word");

        // ========================================================================
        // Test 7: RAM Multiple Address Write/Read
        $display("\n[Test 7] RAM Multiple Address Write/Read:");

        address = 64'h0000_0000_1000_0014;
        write_data = 64'h1972_1121_1984_0315;
        write_mask = 8'b1111_1111;
        write_enable = 1;
        #10;
        write_enable = 0;
        #10;
        check_result(64'h1972_1121_1984_0315, "Write to 0x10000014");

        address = 64'h0000_0000_1000_0004;
        #10;
        check_result(64'hDEAD_BEEF_CAFE_BABE, "Read previous 0x10000004");

        // ========================================================================
        // Test 8: Address Region Boundary Test
        $display("\n[Test 8] Address Region Boundary Test:");
        
        address = 64'h0000_0000_0000_FFFC;
        rom_read_data = 64'hFFFF_FFFF_FFFF_FFFF;
        write_enable = 0;
        #10;
        check_result(64'hFFFF_FFFF_FFFF_FFFF, "ROM boundary 0x0000FFFC");
        
        address = 64'h0000_0000_1000_0000;
        write_data = 64'h1111_1111_2222_2222;
        write_mask = 8'b1111_1111;
        write_enable = 1;
        #10;
        write_enable = 0;
        #10;
        check_result(64'h1111_1111_2222_2222, "RAM boundary 0x10000000");

        // ========================================================================
        // Test 9: Invalid Address Region (not ROM or RAM)
        $display("\n[Test 9] Invalid Address Region:");
        
        address = 64'h0000_0000_2000_0000;
        rom_read_data = 64'h1234_5678_9ABC_DEF0;
        #10;
        check_result(64'h0000_0000_0000_0000, "Invalid 0x20000000");
        
        address = 64'hFFFF_FFFF_FFFF_FFFF;
        #10;
        check_result(64'h0000_0000_0000_0000, "Invalid 0xFFFFFFFFFFFFFFFF");

        // ========================================================================
        // Test 10: ROM vs RAM Read Priority Test
        $display("\n[Test 10] ROM vs RAM Read Priority:");
        
        address = 64'h0000_0000_1000_0020;
        write_data = 64'hAAAA_AAAA_AAAA_AAAA;
        write_mask = 8'b1111_1111;
        write_enable = 1;
        #10;
        write_enable = 0;
        #10;
        check_result(64'hAAAA_AAAA_AAAA_AAAA, "RAM write 0x10000020");
        
        address = 64'h0000_0000_0000_0020;
        rom_read_data = 64'hBBBB_BBBB_BBBB_BBBB;
        #10;
        check_result(64'hBBBB_BBBB_BBBB_BBBB, "ROM read 0x00000020");

        // ========================================================================
        // Test 11: RAM Write Enable Control
        $display("\n[Test 11] RAM Write Enable Control:");

        address = 64'h0000_0000_1000_0024;
        write_data = 64'hDEAD_BEEF_CAFE_BABE;
        write_mask = 8'b1111_1111;
        write_enable = 0;
        #10;
        check_result(64'h0000_0000_0000_0000, "write_enable=0");
        
        write_enable = 1;
        #10;
        write_enable = 0;
        #10;
        check_result(64'hDEAD_BEEF_CAFE_BABE, "write_enable=1");

        // ========================================================================
        // Test 12: ROM Address Output Verification
        $display("\n[Test 12] ROM Address Output Verification:");
        
        address = 64'h0000_0000_0000_0100;
        #10;
        check_rom_address(64'h0000_0000_0000_0100, "rom_address=0x00000100");
        
        address = 64'h0000_0000_0000_2000;
        #10;
        check_rom_address(64'h0000_0000_0000_2000, "rom_address=0x00002000");

        // ========================================================================
        // Test 13: Zero Mask Write (No bytes written)
        $display("\n[Test 13] Zero Mask Write:");

        address = 64'h0000_0000_1000_0028;
        write_data = 64'hFFFF_FFFF_FFFF_FFFF;
        write_mask = 8'b1111_1111;
        write_enable = 1;
        #10;
        write_enable = 0;
        #10;

        write_data = 64'h0000_0000_0000_0000;
        write_mask = 8'b0000_0000;
        write_enable = 1;
        #10;
        write_enable = 0;
        #10;
        check_result(64'hFFFF_FFFF_FFFF_FFFF, "mask=00000000 no write");

        // ========================================================================
        // Test 14: Alternating Byte Pattern Masking
        $display("\n[Test 14] Alternating Byte Pattern:");

        address = 64'h0000_0000_1000_002C;
        write_data = 64'h0000_0000_0000_0000;
        write_mask = 8'b1111_1111;
        write_enable = 1;
        #10;
        write_enable = 0;
        #10;

        // mask = 01010101
        write_data = 64'hAA11_BB22_CC33_DD44;
        write_mask = 8'b0101_0101;
        write_enable = 1;
        #10;
        write_enable = 0;
        #10;
        check_result(64'h0011_0022_0033_0044, "mask=01010101");

        // mask = 10101010
        write_data = 64'hEE55_FF66_0077_1188;
        write_mask = 8'b1010_1010;
        write_enable = 1;
        #10;
        write_enable = 0;
        #10;
        check_result(64'hEE11_FF22_0033_1144, "mask=10101010");

        // ========================================================================
        // Test Summary
        $display("\n==================== Test Summary ====================");
        $display("  Total: %0d | PASSED: %0d | FAILED: %0d", test_num, pass_count, fail_count);
        if (fail_count == 0)
            $display("  *** ALL TESTS PASSED ***");
        else
            $display("  *** SOME TESTS FAILED ***");
        $display("====================  Data Memory Test END  ====================");
        
        $finish;
    end

endmodule

testbenches/results/waveforms/Data_Memory_tb_result.vcd
$date
	Fri Jan 02 23:50:30 2026
$end
$version
	Icarus Verilog
$end
$timescale
	1ps
$end
$scope module DataMemory_tb $end
$scope module data_memory $end
$var wire 64 ! address [63:0] $end
$var wire 1 " clk $end
$var wire 64 # rom_address [63:0] $end
$var wire 64 $ rom_read_data [63:0] $end
$var wire 64 % write_data [63:0] $end
$var wire 1 & write_enable $end
$var wire 8 ' write_mask [7:0] $end
$var wire 1 ( rom_access $end
$var wire 13 ) ram_address [12:0] $end
$var wire 1 * ram_access $end
$var wire 64 + extended_mask [63:0] $end
$var parameter 32 , XLEN $end
$var reg 64 - new_word [63:0] $end
$var reg 64 . read_data [63:0] $end
$var integer 32 / i [31:0] $end
$upscope $end
$upscope $end
$enddefinitions $end
$comment Show the parameter values. $end
$dumpall
b1000000 ,
$end
#0
$dumpvars
b10000000000 /
b0 .
b0 -
b0 +
0*
b0 )
1(
b0 '
0&
b0 %
b0 $
b0 #
0"
b0 !
$end
#5000
1"
#10000
b1001000110100010101100111100010011010101111001101111011110000 .
b1 )
0"
b1001000110100010101100111100010011010101111001101111011110000 $
b100 #
b100 !
#15000
1"
#20000
b1010101111001101111011110000000100100011010001010110011110001001 .
b10000000000 )
0"
b1010101111001101111011110000000100100011010001010110011110001001 $
b1000000000000 #
b1000000000000 !
#25000
1"
#30000
b1100101011111110101110101011111011011110101011011011111011101111 .
b1111111111111 )
0"
b1100101011111110101110101011111011011110101011011011111011101111 $
b1111111111111100 #
b1111111111111100 !
#35000
1"
#40000
b0 .
1*
0(
b1 )
0"
b1101111010101101101111101110111111001010111111101011101010111110 $
b10000000000000000000000000100 #
b10000000000000000000000000100 !
#45000
1"
#50000
b1111111111111111111111111111111111111111111111111111111111111111 +
0"
b1001000110100010101100111100010011010101111001101111011110000 $
1&
b11111111 '
b1101111010101101101111101110111111001010111111101011101010111110 %
#55000
b1101111010101101101111101110111111001010111111101011101010111110 .
b1101111010101101101111101110111111001010111111101011101010111110 -
1"
#60000
0"
0&
#65000
1"
#70000
b0 .
b10 )
0"
1&
b1111111111111111111111111111111111111111111111111111111111111111 %
b10000000000000000000000001000 #
b10000000000000000000000001000 !
#75000
b1111111111111111111111111111111111111111111111111111111111111111 .
b1111111111111111111111111111111111111111111111111111111111111111 -
1"
#80000
0"
0&
#85000
1"
#90000
b11111111 +
0"
1&
b1 '
b1000100100010001100110100010001010101011001100111011110101010 %
#95000
b1111111111111111111111111111111111111111111111111111111110101010 .
b1111111111111111111111111111111111111111111111111111111110101010 -
1"
#100000
0"
0&
#105000
1"
#110000
b1111111100000000 +
0"
1&
b10 '
b1000100100010001100110100010001010101011001101011101110001000 %
#115000
b1111111111111111111111111111111111111111111111111011101110101010 .
b1111111111111111111111111111111111111111111111111011101110101010 -
1"
#120000
0"
0&
#125000
1"
#130000
b111111110000000000000000 +
0"
1&
b100 '
b1000100100010001100110100010001010101110011000111011110001000 %
#135000
b1111111111111111111111111111111111111111110011001011101110101010 .
b1111111111111111111111111111111111111111110011001011101110101010 -
1"
#140000
0"
0&
#145000
1"
#150000
b11111111000000000000000000000000 +
0"
1&
b1000 '
b1000100100010001100110100010011011101011001100111011110001000 %
#155000
b1111111111111111111111111111111111011101110011001011101110101010 .
b1111111111111111111111111111111111011101110011001011101110101010 -
1"
#160000
0"
0&
#165000
1"
#170000
b1111111100000000000000000000000000000000 +
0"
1&
b10000 '
b1000100100010001100111110111001010101011001100111011110001000 %
#175000
b1111111111111111111111111110111011011101110011001011101110101010 .
b1111111111111111111111111110111011011101110011001011101110101010 -
1"
#180000
0"
0&
#185000
1"
#190000
b111111110000000000000000000000000000000000000000 +
0"
1&
b100000 '
b1000100100010111111110100010001010101011001100111011110001000 %
#195000
1"
#200000
0"
0&
#205000
1"
#210000
b11111111000000000000000000000000000000000000000000000000 +
0"
1&
b1000000 '
b1000110101011001100110100010001010101011001100111011110001000 %
#215000
b1111111110101011111111111110111011011101110011001011101110101010 .
b1111111110101011111111111110111011011101110011001011101110101010 -
1"
#220000
0"
0&
#225000
1"
#230000
b1111111100000000000000000000000000000000000000000000000000000000 +
0"
1&
b10000000 '
b1100110100100010001100110100010001010101011001100111011110001000 %
#235000
b1100110110101011111111111110111011011101110011001011101110101010 .
b1100110110101011111111111110111011011101110011001011101110101010 -
1"
#240000
0"
0&
#245000
1"
#250000
b0 .
b1111111111111111111111111111111111111111111111111111111111111111 +
b11 )
0"
1&
b11111111 '
b0 %
b10000000000000000000000001100 #
b10000000000000000000000001100 !
#255000
b0 -
1"
#260000
0"
0&
#265000
1"
#270000
b1111111111111111 +
0"
1&
b11 '
b1010101010101010101110111011101111001100110011001101110111011101 %
#275000
b1101110111011101 .
b1101110111011101 -
1"
#280000
0"
0&
#285000
1"
#290000
b11111111111111110000000000000000 +
0"
1&
b1100 '
b1010101010101010101110111011101111101110111011101111111111111111 %
#295000
b11101110111011101101110111011101 .
b11101110111011101101110111011101 -
1"
#300000
0"
0&
#305000
1"
#310000
b0 .
b11111111111111111111111111111111 +
b100 )
0"
1&
b1111 '
b1000100010001001000100010001000110011001100110100010001000100 %
b10000000000000000000000010000 #
b10000000000000000000000010000 !
#315000
b110011001100110100010001000100 .
b110011001100110100010001000100 -
1"
#320000
0"
0&
#325000
1"
#330000
b1111111111111111111111111111111100000000000000000000000000000000 +
0"
1&
b11110000 '
b101010101010101011001100110011001110111011101111000100010001000 %
#335000
b101010101010101011001100110011000110011001100110100010001000100 .
b101010101010101011001100110011000110011001100110100010001000100 -
1"
#340000
0"
0&
#345000
1"
#350000
b0 .
b1111111111111111111111111111111111111111111111111111111111111111 +
b101 )
0"
1&
b11111111 '
b1100101110010000100010010000100011001100001000000001100010101 %
b10000000000000000000000010100 #
b10000000000000000000000010100 !
#355000
b1100101110010000100010010000100011001100001000000001100010101 .
b1100101110010000100010010000100011001100001000000001100010101 -
1"
#360000
0"
0&
#365000
1"
#370000
b1101111010101101101111101110111111001010111111101011101010111110 .
b1 )
0"
b10000000000000000000000000100 #
b10000000000000000000000000100 !
#375000
1"
#380000
b1111111111111111111111111111111111111111111111111111111111111111 .
0*
1(
b1111111111111 )
0"
b1111111111111111111111111111111111111111111111111111111111111111 $
b1111111111111100 #
b1111111111111100 !
#385000
1"
#390000
b0 .
1*
0(
b0 )
0"
1&
b1000100010001000100010001000100100010001000100010001000100010 %
b10000000000000000000000000000 #
b10000000000000000000000000000 !
#395000
b1000100010001000100010001000100100010001000100010001000100010 .
b1000100010001000100010001000100100010001000100010001000100010 -
1"
#400000
0"
0&
#405000
1"
#410000
b0 .
0*
0"
b1001000110100010101100111100010011010101111001101111011110000 $
b100000000000000000000000000000 #
b100000000000000000000000000000 !
#415000
1"
#420000
b1111111111111 )
0"
b1111111111111111111111111111111111111111111111111111111111111111 #
b1111111111111111111111111111111111111111111111111111111111111111 !
#425000
1"
#430000
1*
b1000 )
0"
1&
b1010101010101010101010101010101010101010101010101010101010101010 %
b10000000000000000000000100000 #
b10000000000000000000000100000 !
#435000
b1010101010101010101010101010101010101010101010101010101010101010 .
b1010101010101010101010101010101010101010101010101010101010101010 -
1"
#440000
0"
0&
#445000
1"
#450000
b1011101110111011101110111011101110111011101110111011101110111011 .
0*
1(
0"
b1011101110111011101110111011101110111011101110111011101110111011 $
b100000 #
b100000 !
#455000
1"
#460000
b0 .
1*
0(
b1001 )
0"
b1101111010101101101111101110111111001010111111101011101010111110 %
b10000000000000000000000100100 #
b10000000000000000000000100100 !
#465000
1"
#470000
0"
1&
#475000
b1101111010101101101111101110111111001010111111101011101010111110 .
b1101111010101101101111101110111111001010111111101011101010111110 -
1"
#480000
0"
0&
#485000
1"
#490000
b1011101110111011101110111011101110111011101110111011101110111011 .
0*
1(
b1000000 )
0"
b100000000 #
b100000000 !
#495000
1"
#500000
b100000000000 )
0"
b10000000000000 #
b10000000000000 !
#505000
1"
#510000
b0 .
1*
0(
b1010 )
0"
1&
b1111111111111111111111111111111111111111111111111111111111111111 %
b10000000000000000000000101000 #
b10000000000000000000000101000 !
#515000
b1111111111111111111111111111111111111111111111111111111111111111 .
b1111111111111111111111111111111111111111111111111111111111111111 -
1"
#520000
0"
0&
#525000
1"
#530000
b0 +
0"
1&
b0 '
b0 %
#535000
1"
#540000
0"
0&
#545000
1"
#550000
b0 .
b1111111111111111111111111111111111111111111111111111111111111111 +
b1011 )
0"
1&
b11111111 '
b10000000000000000000000101100 #
b10000000000000000000000101100 !
#555000
b0 -
1"
#560000
0"
0&
#565000
1"
#570000
b11111111000000001111111100000000111111110000000011111111 +
0"
1&
b1010101 '
b1010101000010001101110110010001011001100001100111101110101000100 %
#575000
b10001000000000010001000000000001100110000000001000100 .
b10001000000000010001000000000001100110000000001000100 -
1"
#580000
0"
0&
#585000
1"
#590000
b1111111100000000111111110000000011111111000000001111111100000000 +
0"
1&
b10101010 '
b1110111001010101111111110110011000000000011101110001000110001000 %
#595000
b1110111000010001111111110010001000000000001100110001000101000100 .
b1110111000010001111111110010001000000000001100110001000101000100 -
1"
#600000
0"
0&
