modules/Hazard_Unit.v
`include "modules/headers/opcode.vh"
`include "modules/headers/trap.vh"

module HazardUnit (
    input clk,
    input reset, 

    input wire trap_done,
    input wire csr_ready,
    input wire standby_mode,
    input wire [2:0] trap_status,
    input wire misaligned_instruction_flush,
    input wire misaligned_memory_flush,
    input wire pth_done_flush,

    input wire [4:0] ID_rs1,
    input wire [4:0] ID_rs2,
    input wire [11:0] ID_raw_imm,
    
    input wire [4:0] MEM_rd,
    input wire MEM_register_write_enable,
    input wire MEM_csr_write_enable,
    input wire [11:0] MEM_csr_write_address,       // MEM_imm[11:0]

    input wire [4:0] WB_rd,
    input wire WB_register_write_enable,
    input wire WB_csr_write_enable,
    input wire [11:0] WB_csr_write_address, // WB_imm[11:0]

    input wire [4:0] EX_rd,
    input wire [6:0] EX_opcode,
    input wire [4:0] EX_rs1,
    input wire [4:0] EX_rs2,
    input wire [11:0] EX_imm,  // EX_imm[11:0]

    input wire EX_csr_write_enable,

    input wire EX_jump,
    input wire branch_prediction_miss,

    // to Forward Unit - ALU forwarding
    output reg [1:0] hazard_mem,
    output reg [1:0] hazard_wb,
    output wire csr_hazard_mem,
    output wire csr_hazard_wb,
    //output reg csr_reg_hazard,

    /// to Forward Unit - Store data forwarding
    output wire store_hazard_mem,
    output wire store_hazard_wb,

    output reg IF_ID_flush,
    output reg ID_EX_flush,
    output reg EX_MEM_flush,
    output reg MEM_WB_flush,
    
    output reg IF_ID_stall,
    output reg ID_EX_stall,
    output reg EX_MEM_stall,
    output reg MEM_WB_stall
);

    // Store instruction detection
    wire is_store = (EX_opcode == `OPCODE_STORE);

    // Store instruction rs2 hazard detections
    assign store_hazard_mem = is_store && mem_hazard_rs2;
    assign store_hazard_wb = is_store && wb_hazard_rs2 && !mem_hazard_rs2;

    // wire reg_csr_hazard = (EX_opcode == `OPCODE_ENVIRONMENT && (WB_rd == retire_rd) && (WB_csr_write_address == retire_csr_write_address));

    // Register ALU hazard detections
    wire mem_hazard_rs1 = MEM_register_write_enable && (MEM_rd != 5'd0) && (MEM_rd == EX_rs1);
    wire mem_hazard_rs2 = MEM_register_write_enable && (MEM_rd != 5'd0) && (MEM_rd == EX_rs2);
    wire wb_hazard_rs1 = WB_register_write_enable && (WB_rd != 5'd0) && (WB_rd == EX_rs1);
    wire wb_hazard_rs2 = WB_register_write_enable && (WB_rd != 5'd0) && (WB_rd == EX_rs2);
    
    // CSR hazard detection
    assign csr_hazard_mem = MEM_csr_write_enable && (MEM_csr_write_address == EX_imm);
    assign csr_hazard_wb = WB_csr_write_enable && (WB_csr_write_address == EX_imm);

    reg [4:0] retire_rd;
    reg [11:0] retire_csr_write_address;

    always @(posedge clk or posedge reset) begin
        if (reset) begin
            retire_rd <= 5'b0;
            retire_csr_write_address <= 12'b0;    
        end 
        else begin
            retire_rd <= WB_rd;
            retire_csr_write_address <= WB_csr_write_address;
        end
        
    end 

    always @(*) begin
        //csr_reg_hazard = 1'b0;
        hazard_mem = 2'b00;
        hazard_wb = 2'b00;
        IF_ID_flush = 1'b0;
        ID_EX_flush = 1'b0;
        EX_MEM_flush = 1'b0;
        MEM_WB_flush = 1'b0;
        
        IF_ID_stall = 1'b0;
        ID_EX_stall = 1'b0;
        EX_MEM_stall = 1'b0;
        MEM_WB_stall = 1'b0;

        // ALU forwarding hazards
        // For Store instructions, rs2 hazard shouldn't trigger ALUsrcB forwarding.
        // In this case, rs2 is store data, not ALU operand.
        hazard_mem[0] = mem_hazard_rs1;
        hazard_mem[1] = is_store ? 1'b0 : mem_hazard_rs2; // Disables ALUsrcB forwarding for store
        hazard_wb[0] = wb_hazard_rs1 && !mem_hazard_rs1;
        hazard_wb[1] = is_store ? 1'b0 : (wb_hazard_rs2 && !mem_hazard_rs2); // Disables ALUsrcB forwarding for store

        /*if (reg_csr_hazard) begin
            csr_reg_hazard = 1'b1;
        end*/

        if (trap_done && (branch_prediction_miss || EX_jump)) begin
            IF_ID_flush = 1'b1;
            ID_EX_flush = 1'b1;
        end

        if (pth_done_flush) begin
            IF_ID_flush = 1'b1;
            ID_EX_flush = 1'b1;
            EX_MEM_flush = 1'b1;
            MEM_WB_flush = 1'b1;
        end

        if (standby_mode) begin // For ID Phase Excpetion handling
            IF_ID_stall = 1'b1;
            ID_EX_stall = 1'b1;
            EX_MEM_stall = 1'b0;
            MEM_WB_stall = 1'b0;
        end 
        else if (!trap_done || !csr_ready) begin
            IF_ID_stall = 1'b1;
            ID_EX_stall = 1'b1;
            EX_MEM_stall = 1'b1;
            MEM_WB_stall = 1'b1;
        end
    end


    
endmodule

testbenches/Hazard_Unit_tb.v
`timescale 1ns/1ps

`include "modules/headers/opcode.vh"
`include "modules/headers/trap.vh"

module HazardUnit_tb;
    reg clk = 0;
    reg reset = 0;
    
    // Trap and CSR control signals
    reg trap_done;
    reg csr_ready;
    reg standby_mode;
    reg [2:0] trap_status;
    reg misaligned_instruction_flush;
    reg misaligned_memory_flush;
    reg pth_done_flush;

    // ID stage signals
    reg [4:0] ID_rs1;
    reg [4:0] ID_rs2;
    reg [11:0] ID_raw_imm;

    // MEM stage signals
    reg [4:0] MEM_rd;
    reg MEM_register_write_enable;
    reg MEM_csr_write_enable;
    reg [11:0] MEM_csr_write_address;

    // WB stage signals
    reg [4:0] WB_rd;
    reg WB_register_write_enable;
    reg WB_csr_write_enable;
    reg [11:0] WB_csr_write_address;

    // EX stage signals
    reg [4:0] EX_rd;
    reg [6:0] EX_opcode;
    reg [4:0] EX_rs1;
    reg [4:0] EX_rs2;
    reg [11:0] EX_imm;
    reg EX_csr_write_enable;

    // Control signals
    reg EX_jump;
    reg branch_prediction_miss; 

    // Outputs - ALU forwarding
    wire [1:0] hazard_mem;
    wire [1:0] hazard_wb;
    wire csr_hazard_mem;
    wire csr_hazard_wb;

    // Outputs - Store data forwarding
    wire store_hazard_mem;
    wire store_hazard_wb;

    // Outputs - Flush signals
    wire IF_ID_flush;
    wire ID_EX_flush;
    wire EX_MEM_flush;
    wire MEM_WB_flush;

    // Outputs - Stall signals
    wire IF_ID_stall;
    wire ID_EX_stall;
    wire EX_MEM_stall;
    wire MEM_WB_stall;

    HazardUnit dut (
        .clk(clk),
        .reset(reset),
        .trap_done(trap_done),
        .csr_ready(csr_ready),
        .standby_mode(standby_mode),
        .trap_status(trap_status),
        .misaligned_instruction_flush(misaligned_instruction_flush),
        .misaligned_memory_flush(misaligned_memory_flush),
        .pth_done_flush(pth_done_flush),
        .ID_rs1(ID_rs1),
        .ID_rs2(ID_rs2),
        .ID_raw_imm(ID_raw_imm),
        .MEM_rd(MEM_rd),
        .MEM_register_write_enable(MEM_register_write_enable),
        .MEM_csr_write_enable(MEM_csr_write_enable),
        .MEM_csr_write_address(MEM_csr_write_address),
        .WB_rd(WB_rd),
        .WB_register_write_enable(WB_register_write_enable),
        .WB_csr_write_enable(WB_csr_write_enable),
        .WB_csr_write_address(WB_csr_write_address),
        .EX_rd(EX_rd),
        .EX_opcode(EX_opcode),
        .EX_rs1(EX_rs1),
        .EX_rs2(EX_rs2),
        .EX_imm(EX_imm),
        .EX_csr_write_enable(EX_csr_write_enable),
        .EX_jump(EX_jump),
        .branch_prediction_miss(branch_prediction_miss),

        .hazard_mem(hazard_mem),
        .hazard_wb(hazard_wb),
        .csr_hazard_mem(csr_hazard_mem),
        .csr_hazard_wb(csr_hazard_wb),
        .store_hazard_mem(store_hazard_mem),
        .store_hazard_wb(store_hazard_wb),
        .IF_ID_flush(IF_ID_flush),
        .ID_EX_flush(ID_EX_flush),
        .EX_MEM_flush(EX_MEM_flush),
        .MEM_WB_flush(MEM_WB_flush),
        .IF_ID_stall(IF_ID_stall),
        .ID_EX_stall(ID_EX_stall),
        .EX_MEM_stall(EX_MEM_stall),
        .MEM_WB_stall(MEM_WB_stall)
    );

    always #5 clk = ~clk;

    // Task to reset all inputs to default state
    task reset_inputs;
    begin
        trap_done = 1'b1;
        csr_ready = 1'b1;
        standby_mode = 1'b0;
        trap_status = `TRAP_NONE;
        misaligned_instruction_flush = 1'b0;
        misaligned_memory_flush = 1'b0;
        pth_done_flush = 1'b0;
        ID_rs1 = 5'd0;
        ID_rs2 = 5'd0;
        ID_raw_imm = 12'd0;
        MEM_rd = 5'd0;
        MEM_register_write_enable = 1'b0;
        MEM_csr_write_enable = 1'b0;
        MEM_csr_write_address = 12'd0;
        WB_rd = 5'd0;
        WB_register_write_enable = 1'b0;
        WB_csr_write_enable = 1'b0;
        WB_csr_write_address = 12'd0;
        EX_rd = 5'd0;
        EX_opcode = `OPCODE_RTYPE;
        EX_rs1 = 5'd0;
        EX_rs2 = 5'd0;
        EX_imm = 12'd0;
        EX_csr_write_enable = 1'b0;
        EX_jump = 1'b0;
        branch_prediction_miss = 1'b0;
    end
    endtask

    initial begin
        $dumpfile("testbenches/results/waveforms/Hazard_Unit_tb_result.vcd");
        $dumpvars(0, HazardUnit_tb.dut);

        $display("==================== Hazard Unit Test START ====================\n");

        // reset signals
        reset = 1'b1;
        reset_inputs();
        #10;
        
        reset = 1'b0;
        @(posedge clk);

        // ===================== ALU Forwarding Tests =====================

        // Test 1 : No RAW hazard
        $display("Test 1 (No hazard)");
        reset_inputs();
        EX_rs1 = 5'd1;
        EX_rs2 = 5'd2;
        MEM_rd = 5'd3;
        MEM_register_write_enable = 1'b1;
        WB_rd = 5'd4;
        WB_register_write_enable = 1'b1;
        @(posedge clk);
        $display("hazard_mem = %b (expect 00)", hazard_mem);
        $display("hazard_wb  = %b (expect 00)", hazard_wb);
        $display("IF_ID_flush  = %b", IF_ID_flush);
        $display("ID_EX_flush  = %b\n", ID_EX_flush);
        
        // Test 2 : MEM stage rs1 hazard (MEM_rd == EX_rs1)
        $display("Test 2 (MEM rs1 hazard)");
        reset_inputs();
        EX_rs1 = 5'd3;
        EX_rs2 = 5'd4;
        MEM_rd = 5'd3;
        MEM_register_write_enable = 1'b1;
        @(posedge clk);
        $display("hazard_mem = %b (expect 01)", hazard_mem);
        $display("hazard_wb  = %b (expect 00)", hazard_wb);
        $display("IF_ID_flush  = %b (expect 0)", IF_ID_flush);
        $display("ID_EX_flush  = %b (expect 0)\n", ID_EX_flush);

        // Test 3 : MEM stage rs2 hazard (MEM_rd == EX_rs2)
        $display("Test 3 (MEM rs2 hazard)");
        reset_inputs();
        EX_rs1 = 5'd6;
        EX_rs2 = 5'd5;
        MEM_rd = 5'd5;
        MEM_register_write_enable = 1'b1;
        @(posedge clk);
        $display("hazard_mem = %b (expect 10)", hazard_mem);
        $display("hazard_wb  = %b (expect 00)", hazard_wb);
        $display("IF_ID_flush  = %b (expect 0)", IF_ID_flush);
        $display("ID_EX_flush  = %b (expect 0)\n", ID_EX_flush);

        // Test 4 : WB stage rs1 hazard (WB_rd == EX_rs1, no MEM hazard)
        $display("Test 4 (WB rs1 hazard)");
        reset_inputs();
        EX_rs1 = 5'd7;
        EX_rs2 = 5'd8;
        WB_rd = 5'd7;
        WB_register_write_enable = 1'b1;
        MEM_rd = 5'd9;
        MEM_register_write_enable = 1'b1;
        @(posedge clk);
        $display("hazard_mem = %b (expect 00)", hazard_mem);
        $display("hazard_wb  = %b (expect 01)", hazard_wb);
        $display("IF_ID_flush  = %b (expect 0)", IF_ID_flush);
        $display("ID_EX_flush  = %b (expect 0)\n", ID_EX_flush);

        // Test 5 : Both MEM rs1/rs2 hazards
        $display("Test 5 (MEM both rs1/rs2 hazard)");
        reset_inputs();
        EX_rs1 = 5'd7;
        EX_rs2 = 5'd7;
        MEM_rd = 5'd7;
        MEM_register_write_enable = 1'b1;
        @(posedge clk);
        $display("hazard_mem = %b (expect 11)", hazard_mem);
        $display("hazard_wb  = %b (expect 00)", hazard_wb);
        $display("IF_ID_flush  = %b (expect 0)", IF_ID_flush);
        $display("ID_EX_flush  = %b (expect 0)\n", ID_EX_flush);

        // Test 6 : MEM priority over WB (same register)
        $display("Test 6 (MEM priority over WB)");
        reset_inputs();
        EX_rs1 = 5'd10;
        EX_rs2 = 5'd11;
        MEM_rd = 5'd10;
        MEM_register_write_enable = 1'b1;
        WB_rd = 5'd10;
        WB_register_write_enable = 1'b1;
        @(posedge clk);
        $display("hazard_mem = %b (expect 01)", hazard_mem);
        $display("hazard_wb  = %b (expect 00, MEM has priority)", hazard_wb);
        $display("IF_ID_flush  = %b (expect 0)", IF_ID_flush);
        $display("ID_EX_flush  = %b (expect 0)\n", ID_EX_flush);

        // ===================== Store Data Forwarding Tests =====================

        // Test 7 : Store instruction - MEM stage rs2 hazard (store data forwarding)
        $display("Test 7 (Store MEM rs2 hazard - store data forwarding)");
        reset_inputs();
        EX_opcode = `OPCODE_STORE;
        EX_rs1 = 5'd1;
        EX_rs2 = 5'd5;  // store data register
        MEM_rd = 5'd5;
        MEM_register_write_enable = 1'b1;
        @(posedge clk);
        $display("hazard_mem = %b (expect 00, store disables ALUsrcB)", hazard_mem);
        $display("store_hazard_mem = %b (expect 1)", store_hazard_mem);
        $display("store_hazard_wb  = %b (expect 0)\n", store_hazard_wb);

        // Test 8 : Store instruction - WB stage rs2 hazard
        $display("Test 8 (Store WB rs2 hazard - store data forwarding)");
        reset_inputs();
        EX_opcode = `OPCODE_STORE;
        EX_rs1 = 5'd1;
        EX_rs2 = 5'd6;  // store data register
        WB_rd = 5'd6;
        WB_register_write_enable = 1'b1;
        @(posedge clk);
        $display("hazard_wb = %b (expect 00, store disables ALUsrcB)", hazard_wb);
        $display("store_hazard_mem = %b (expect 0)", store_hazard_mem);
        $display("store_hazard_wb  = %b (expect 1)\n", store_hazard_wb);

        // ===================== CSR Hazard Tests =====================

        // Test 9 : CSR hazard from MEM stage
        $display("Test 9 (CSR hazard MEM)");
        reset_inputs();
        EX_imm = 12'h305;  // mtvec address
        MEM_csr_write_enable = 1'b1;
        MEM_csr_write_address = 12'h305;
        @(posedge clk);
        $display("csr_hazard_mem = %b (expect 1)", csr_hazard_mem);
        $display("csr_hazard_wb  = %b (expect 0)\n", csr_hazard_wb);

        // Test 10 : CSR hazard from WB stage
        $display("Test 10 (CSR hazard WB)");
        reset_inputs();
        EX_imm = 12'h341;  // mepc address
        WB_csr_write_enable = 1'b1;
        WB_csr_write_address = 12'h341;
        @(posedge clk);
        $display("csr_hazard_mem = %b (expect 0)", csr_hazard_mem);
        $display("csr_hazard_wb  = %b (expect 1)\n", csr_hazard_wb);

        // ===================== Flush Tests =====================

        // Test 11 : Branch prediction miss flush
        $display("Test 11 (Branch prediction miss flush)");
        reset_inputs();
        branch_prediction_miss = 1'b1;
        @(posedge clk);
        $display("IF_ID_flush  = %b (expect 1)", IF_ID_flush);
        $display("ID_EX_flush  = %b (expect 1)", ID_EX_flush);
        $display("EX_MEM_flush = %b (expect 0)", EX_MEM_flush);
        $display("MEM_WB_flush = %b (expect 0)\n", MEM_WB_flush);

        // Test 12 : Jump flush
        $display("Test 12 (Jump flush)");
        reset_inputs();
        EX_jump = 1'b1;
        @(posedge clk);
        $display("IF_ID_flush  = %b (expect 1)", IF_ID_flush);
        $display("ID_EX_flush  = %b (expect 1)", ID_EX_flush);
        $display("EX_MEM_flush = %b (expect 0)", EX_MEM_flush);
        $display("MEM_WB_flush = %b (expect 0)\n", MEM_WB_flush);

        // Test 13 : PTH done flush (all stages)
        $display("Test 13 (PTH done flush - all stages)");
        reset_inputs();
        pth_done_flush = 1'b1;
        @(posedge clk);
        $display("IF_ID_flush  = %b (expect 1)", IF_ID_flush);
        $display("ID_EX_flush  = %b (expect 1)", ID_EX_flush);
        $display("EX_MEM_flush = %b (expect 1)", EX_MEM_flush);
        $display("MEM_WB_flush = %b (expect 1)\n", MEM_WB_flush);

        // ===================== Stall Tests =====================

        // Test 14 : Standby mode stall (ID phase exception handling)
        $display("Test 14 (Standby mode stall)");
        reset_inputs();
        standby_mode = 1'b1;
        @(posedge clk);
        $display("IF_ID_stall  = %b (expect 1)", IF_ID_stall);
        $display("ID_EX_stall  = %b (expect 1)", ID_EX_stall);
        $display("EX_MEM_stall = %b (expect 0)", EX_MEM_stall);
        $display("MEM_WB_stall = %b (expect 0)\n", MEM_WB_stall);

        // Test 15 : trap_done = 0 stall (all stages)
        $display("Test 15 (trap_done=0 stall - all stages)");
        reset_inputs();
        trap_done = 1'b0;
        @(posedge clk);
        $display("IF_ID_stall  = %b (expect 1)", IF_ID_stall);
        $display("ID_EX_stall  = %b (expect 1)", ID_EX_stall);
        $display("EX_MEM_stall = %b (expect 1)", EX_MEM_stall);
        $display("MEM_WB_stall = %b (expect 1)\n", MEM_WB_stall);

        // Test 16 : csr_ready = 0 stall (all stages)
        $display("Test 16 (csr_ready=0 stall - all stages)");
        reset_inputs();
        csr_ready = 1'b0;
        @(posedge clk);
        $display("IF_ID_stall  = %b (expect 1)", IF_ID_stall);
        $display("ID_EX_stall  = %b (expect 1)", ID_EX_stall);
        $display("EX_MEM_stall = %b (expect 1)", EX_MEM_stall);
        $display("MEM_WB_stall = %b (expect 1)\n", MEM_WB_stall);

        // ===================== Edge Case Tests =====================

        // Test 17 : x0 register should not cause hazard
        $display("Test 17 (x0 no hazard)");
        reset_inputs();
        EX_rs1 = 5'd0;
        EX_rs2 = 5'd0;
        MEM_rd = 5'd0;
        MEM_register_write_enable = 1'b1;
        @(posedge clk);
        $display("hazard_mem = %b (expect 00, x0 no hazard)", hazard_mem);
        $display("hazard_wb  = %b (expect 00)\n", hazard_wb);

        // Test 18 : No hazard when write enable is 0
        $display("Test 18 (Write enable=0 no hazard)");
        reset_inputs();
        EX_rs1 = 5'd5;
        EX_rs2 = 5'd5;
        MEM_rd = 5'd5;
        MEM_register_write_enable = 1'b0;  // write disabled
        @(posedge clk);
        $display("hazard_mem = %b (expect 00, WE=0)", hazard_mem);
        $display("hazard_wb  = %b (expect 00)\n", hazard_wb);

        // Test 19 : Normal operation (no stall, no flush)
        $display("Test 19 (Normal operation)");
        reset_inputs();
        @(posedge clk);
        $display("IF_ID_flush  = %b (expect 0)", IF_ID_flush);
        $display("ID_EX_flush  = %b (expect 0)", ID_EX_flush);
        $display("EX_MEM_flush = %b (expect 0)", EX_MEM_flush);
        $display("MEM_WB_flush = %b (expect 0)", MEM_WB_flush);
        $display("IF_ID_stall  = %b (expect 0)", IF_ID_stall);
        $display("ID_EX_stall  = %b (expect 0)", ID_EX_stall);
        $display("EX_MEM_stall = %b (expect 0)", EX_MEM_stall);
        $display("MEM_WB_stall = %b (expect 0)\n", MEM_WB_stall);

        $display("==================== Hazard Unit Test END ====================\n");
        $stop;
    end

endmodule

testbenches/results/waveforms/Hazard_Unit_tb_result.vcd
$date
	Tue Dec 30 00:22:21 2025
$end
$version
	Icarus Verilog
$end
$timescale
	1ps
$end
$scope module HazardUnit_tb $end
$scope module dut $end
$var wire 1 ! EX_csr_write_enable $end
$var wire 12 " EX_imm [11:0] $end
$var wire 1 # EX_jump $end
$var wire 7 $ EX_opcode [6:0] $end
$var wire 5 % EX_rd [4:0] $end
$var wire 5 & EX_rs1 [4:0] $end
$var wire 5 ' EX_rs2 [4:0] $end
$var wire 12 ( ID_raw_imm [11:0] $end
$var wire 5 ) ID_rs1 [4:0] $end
$var wire 5 * ID_rs2 [4:0] $end
$var wire 12 + MEM_csr_write_address [11:0] $end
$var wire 1 , MEM_csr_write_enable $end
$var wire 5 - MEM_rd [4:0] $end
$var wire 1 . MEM_register_write_enable $end
$var wire 12 / WB_csr_write_address [11:0] $end
$var wire 1 0 WB_csr_write_enable $end
$var wire 5 1 WB_rd [4:0] $end
$var wire 1 2 WB_register_write_enable $end
$var wire 1 3 branch_prediction_miss $end
$var wire 1 4 clk $end
$var wire 1 5 csr_hazard_mem $end
$var wire 1 6 csr_hazard_wb $end
$var wire 1 7 csr_ready $end
$var wire 1 8 mem_hazard_rs1 $end
$var wire 1 9 mem_hazard_rs2 $end
$var wire 1 : misaligned_instruction_flush $end
$var wire 1 ; misaligned_memory_flush $end
$var wire 1 < pth_done_flush $end
$var wire 1 = reset $end
$var wire 1 > standby_mode $end
$var wire 1 ? store_hazard_mem $end
$var wire 1 @ store_hazard_wb $end
$var wire 1 A trap_done $end
$var wire 3 B trap_status [2:0] $end
$var wire 1 C wb_hazard_rs1 $end
$var wire 1 D wb_hazard_rs2 $end
$var wire 1 E is_store $end
$var reg 1 F EX_MEM_flush $end
$var reg 1 G EX_MEM_stall $end
$var reg 1 H ID_EX_flush $end
$var reg 1 I ID_EX_stall $end
$var reg 1 J IF_ID_flush $end
$var reg 1 K IF_ID_stall $end
$var reg 1 L MEM_WB_flush $end
$var reg 1 M MEM_WB_stall $end
$var reg 2 N hazard_mem [1:0] $end
$var reg 2 O hazard_wb [1:0] $end
$var reg 12 P retire_csr_write_address [11:0] $end
$var reg 5 Q retire_rd [4:0] $end
$upscope $end
$upscope $end
$enddefinitions $end
$comment Show the parameter values. $end
$dumpall
$end
#0
$dumpvars
b0 Q
b0 P
b0 O
b0 N
0M
0L
0K
0J
0I
0H
0G
0F
0E
0D
0C
b0 B
1A
0@
0?
0>
1=
0<
0;
0:
09
08
17
06
05
04
03
02
b0 1
00
b0 /
0.
b0 -
0,
b0 +
b0 *
b0 )
b0 (
b0 '
b0 &
b0 %
b110011 $
0#
b0 "
0!
$end
#5000
14
#10000
04
0=
#15000
b100 Q
12
b100 1
1.
b11 -
b10 '
b1 &
14
#20000
04
#25000
b0 Q
b1 N
18
b100 '
b11 &
02
b0 1
1.
b11 -
14
#30000
04
#35000
b10 N
19
08
b101 '
b110 &
1.
b101 -
14
#40000
04
#45000
b111 Q
b1 O
1C
b0 N
09
12
b111 1
b1000 '
b111 &
1.
b1001 -
14
#50000
04
#55000
b0 Q
b11 N
b0 O
19
18
0C
b111 '
b111 &
02
b0 1
1.
b111 -
14
#60000
04
#65000
b1010 Q
1C
b1 N
09
12
b1010 1
b1011 '
b1010 &
1.
b1010 -
14
#70000
04
#75000
b0 Q
1?
b0 N
19
0C
08
1E
b100011 $
b101 '
b1 &
02
b0 1
1.
b101 -
14
#80000
04
#85000
b110 Q
1@
1D
0?
09
12
b110 1
b110 '
b1 &
1E
b100011 $
0.
b0 -
14
#90000
04
#95000
b0 Q
0@
0D
15
b0 O
b1100000101 +
1,
b1100000101 "
b0 '
b0 &
0E
b110011 $
02
b0 1
14
#100000
04
#105000
b1101000001 P
16
05
b1101000001 /
10
b1101000001 "
b0 +
0,
14
#110000
04
#115000
b0 P
1H
1J
06
13
b0 "
b0 /
00
14
#120000
04
#125000
1H
1J
1#
03
14
#130000
04
#135000
1L
1F
1H
1J
1<
0#
14
#140000
04
#145000
1I
1K
0L
0F
0H
0J
1>
0<
14
#150000
04
#155000
1M
1G
1I
1K
0A
0>
14
#160000
04
#165000
1M
1G
1I
1K
07
1A
14
#170000
04
#175000
0M
0G
0I
0K
1.
17
14
#180000
04
#185000
b101 -
b101 '
b101 &
0.
14
#190000
04
#195000
b0 '
b0 &
b0 -
14
