modules/ID_EX_Register.v
module ID_EX_Register #(
    parameter XLEN = 64
)(
    // pipeline register control signals
    input wire clk,
    input wire reset,
    input wire flush,
    input wire ID_EX_stall,

    // signal from IF phase
    // input wire [XLEN-1:0] IF_PC but why? What was this for?

    // signals from IF/ID register
    input wire [XLEN-1:0] ID_pc,
    input wire [XLEN-1:0] ID_pc_plus_4,
    input wire ID_branch_estimation,
    input wire [31:0] ID_instruction,

    // signals from ID phase
    input wire ID_jump,
    input wire ID_branch,
    input wire [1:0] ID_alu_src_A_select,
    input wire [2:0] ID_alu_src_B_select,
    input wire ID_memory_read,
    input wire ID_memory_write,
    input wire [2:0] ID_register_file_write_data_select,
    input wire ID_register_write_enable,
    input wire ID_csr_write_enable,
    input wire [6:0] ID_opcode, 
    input wire [2:0] ID_funct3,
    input wire [6:0] ID_funct7,
    input wire [4:0] ID_rd,
    input wire [19:0] ID_raw_imm,
    input wire [XLEN-1:0] ID_read_data1,
    input wire [XLEN-1:0] ID_read_data2,
    input wire [4:0] ID_rs1,
    input wire [4:0] ID_rs2,
    input wire [XLEN-1:0] ID_imm,
    input wire [XLEN-1:0] ID_csr_read_data,

    // signals to EX/MEM register
    output reg [XLEN-1:0] EX_pc,
    output reg [XLEN-1:0] EX_pc_plus_4,
    output reg EX_branch_estimation,
    output reg [31:0] EX_instruction,

    output reg EX_jump,
    output reg EX_memory_read,
    output reg EX_memory_write,
    output reg [2:0] EX_register_file_write_data_select,
    output reg EX_register_write_enable,
    output reg EX_csr_write_enable,
    output reg EX_branch,
    output reg [1:0] EX_alu_src_A_select,
    output reg [2:0] EX_alu_src_B_select,
    output reg [6:0] EX_opcode,
    output reg [2:0] EX_funct3,
    output reg [6:0] EX_funct7,
    output reg [4:0] EX_rd,
    output reg [19:0] EX_raw_imm,
    output reg [XLEN-1:0] EX_read_data1,
    output reg [XLEN-1:0] EX_read_data2,
    output reg [4:0] EX_rs1,
    output reg [4:0] EX_rs2,
    output reg [XLEN-1:0] EX_imm,
    output reg [XLEN-1:0] EX_csr_read_data
);

always @(posedge clk or posedge reset) begin
    if (reset) begin
        EX_pc <= {XLEN{1'b0}};
        EX_pc_plus_4 <= {XLEN{1'b0}};
        EX_branch_estimation <= 1'b0;
        EX_instruction <= 32'h0000_0013; // ADDI x0, x0, 0 = RISC-V NOP, HINT

        EX_jump <= 1'b0;
        EX_memory_read <= 1'b0;
        EX_memory_write <= 1'b0;
        EX_register_file_write_data_select <= 3'b0;
        EX_register_write_enable <= 1'b0;
        EX_csr_write_enable <= 1'b0;
        EX_branch <= 1'b0;
        EX_alu_src_A_select <= 2'b0;
        EX_alu_src_B_select <= 3'b0;
        EX_opcode <= 7'b0;
        EX_funct3 <= 3'b0;
        EX_funct7 <= 7'b0;
        EX_rd <= 5'b0;
        EX_raw_imm <= 20'b0;
        EX_read_data1 <= {XLEN{1'b0}};
        EX_read_data2 <= {XLEN{1'b0}};
        EX_rs1 <= 5'b0;
        EX_rs2 <= 5'b0;
        EX_imm <= {XLEN{1'b0}};
        EX_csr_read_data <= {XLEN{1'b0}};
    end else begin
        if (flush) begin
            EX_pc <= {XLEN{1'b0}};
            EX_pc_plus_4 <= {XLEN{1'b0}};
            EX_branch_estimation <= 1'b0;
            EX_instruction <= 32'h0000_0013; // ADDI x0, x0, 0 = RISC-V NOP, HINT

            EX_jump <= 1'b0;
            EX_memory_read <= 1'b0;
            EX_memory_write <= 1'b0;
            EX_register_file_write_data_select <= 3'b0;
            EX_register_write_enable <= 1'b0;
            EX_csr_write_enable <= 1'b0;
            EX_branch <= 1'b0;
            EX_alu_src_A_select <= 2'b0;
            EX_alu_src_B_select <= 3'b0;
            EX_opcode <= 7'b0;
            EX_funct3 <= 3'b0;
            EX_funct7 <= 7'b0;
            EX_rd <= 5'b0;
            EX_raw_imm <= 20'b0;
            EX_read_data1 <= {XLEN{1'b0}};
            EX_read_data2 <= {XLEN{1'b0}};
            EX_rs1 <= 5'b0;
            EX_rs2 <= 5'b0;
            EX_imm <= {XLEN{1'b0}};
            EX_csr_read_data <= {XLEN{1'b0}};
        end else if (!ID_EX_stall) begin
            EX_pc <= ID_pc;
            EX_pc_plus_4 <= ID_pc_plus_4;
            EX_branch_estimation <= ID_branch_estimation;
            EX_instruction <= ID_instruction;

            EX_jump <= ID_jump;
            EX_memory_read <= ID_memory_read;
            EX_memory_write <= ID_memory_write;
            EX_register_file_write_data_select <= ID_register_file_write_data_select;
            EX_register_write_enable <= ID_register_write_enable;
            EX_csr_write_enable <= ID_csr_write_enable;
            EX_branch <= ID_branch;
            EX_alu_src_A_select <= ID_alu_src_A_select;
            EX_alu_src_B_select <= ID_alu_src_B_select;
            EX_opcode <= ID_opcode;
            EX_funct3 <= ID_funct3;
            EX_funct7 <= ID_funct7;
            EX_rd <= ID_rd;
            EX_raw_imm <= ID_raw_imm;
            EX_read_data1 <= ID_read_data1;
            EX_read_data2 <= ID_read_data2;
            EX_rs1 <= ID_rs1;
            EX_rs2 <= ID_rs2;
            EX_imm <= ID_imm;
            EX_csr_read_data <= ID_csr_read_data;
        end 
    end 
end

endmodule

testbenches/ID_EX_Register_tb.v
`timescale 1ns/1ps

module ID_EX_Register_tb;
    localparam XLEN = 64;

    reg clk = 0;
    reg reset = 0;
    reg flush = 0;
    reg ID_EX_stall = 0;

    reg [XLEN-1:0] ID_pc;
    reg [XLEN-1:0] ID_pc_plus_4;
    reg ID_branch_estimation;

    reg ID_jump;
    reg ID_branch;
    reg [1:0] ID_alu_src_A_select;
    reg [2:0] ID_alu_src_B_select;
    reg ID_memory_read;
    reg ID_memory_write;
    reg [2:0] ID_register_file_write_data_select;
    reg ID_register_write_enable;
    reg ID_csr_write_enable;
    reg [6:0] ID_opcode; 
    reg [2:0] ID_funct3;
    reg [6:0] ID_funct7;
    reg [4:0] ID_rd;
    reg [19:0] ID_raw_imm;
    reg [XLEN-1:0] ID_read_data1;
    reg [XLEN-1:0] ID_read_data2;
    reg [4:0] ID_rs1;
    reg [XLEN-1:0] ID_imm;
    reg [XLEN-1:0] ID_csr_read_data;

    wire [XLEN-1:0] EX_pc;
    wire [XLEN-1:0] EX_pc_plus_4;
    wire EX_branch_estimation;

    wire EX_jump;
    wire EX_memory_read;
    wire EX_memory_write;
    wire [2:0] EX_register_file_write_data_select;
    wire EX_register_write_enable;
    wire EX_csr_write_enable;
    wire EX_branch;
    wire [1:0] EX_alu_src_A_select;
    wire [2:0] EX_alu_src_B_select;
    wire [6:0] EX_opcode;
    wire [2:0] EX_funct3;
    wire [6:0] EX_funct7;
    wire [4:0] EX_rd;
    wire [19:0] EX_raw_imm;
    wire [XLEN-1:0] EX_read_data1;
    wire [XLEN-1:0] EX_read_data2;
    wire [4:0] EX_rs1;
    wire [XLEN-1:0] EX_imm;
    wire [XLEN-1:0] EX_csr_read_data;

    ID_EX_Register #(.XLEN(64)) dut (
        .clk(clk),
		.reset(reset),
        .flush(flush),
        .ID_EX_stall(ID_EX_stall),

        .ID_pc(ID_pc),
        .ID_pc_plus_4(ID_pc_plus_4),
        .ID_branch_estimation(ID_branch_estimation),

        .ID_jump(ID_jump),
        .ID_branch(ID_branch),
        .ID_alu_src_A_select(ID_alu_src_A_select),
        .ID_alu_src_B_select(ID_alu_src_B_select),
        .ID_memory_read(ID_memory_read),
        .ID_memory_write(ID_memory_write),
        .ID_register_file_write_data_select(ID_register_file_write_data_select),
        .ID_register_write_enable(ID_register_write_enable),
        .ID_csr_write_enable(ID_csr_write_enable),
        .ID_opcode(ID_opcode), 
        .ID_funct3(ID_funct3),
        .ID_funct7(ID_funct7),
        .ID_rd(ID_rd),
        .ID_raw_imm(ID_raw_imm),
        .ID_read_data1(ID_read_data1),
        .ID_read_data2(ID_read_data2),
        .ID_rs1(ID_rs1),
        .ID_imm(ID_imm),
        .ID_csr_read_data(ID_csr_read_data),

        .EX_pc(EX_pc),
        .EX_pc_plus_4(EX_pc_plus_4),
        .EX_branch_estimation(EX_branch_estimation),

        .EX_jump(EX_jump),
        .EX_memory_read(EX_memory_read),
        .EX_memory_write(EX_memory_write),
        .EX_register_file_write_data_select(EX_register_file_write_data_select),
        .EX_register_write_enable(EX_register_write_enable),
        .EX_csr_write_enable(EX_csr_write_enable),
        .EX_branch(EX_branch),
        .EX_alu_src_A_select(EX_alu_src_A_select),
        .EX_alu_src_B_select(EX_alu_src_B_select),
        .EX_opcode(EX_opcode),
        .EX_funct3(EX_funct3),
        .EX_funct7(EX_funct7),
        .EX_rd(EX_rd),
        .EX_raw_imm(EX_raw_imm),
        .EX_read_data1(EX_read_data1),
        .EX_read_data2(EX_read_data2),
        .EX_rs1(EX_rs1),
        .EX_imm(EX_imm),
        .EX_csr_read_data(EX_csr_read_data)
    );

    always #5 clk = ~clk;

    initial begin
        $dumpfile("testbenches/results/waveforms/ID_EX_Register_tb_result.vcd");
        $dumpvars(0, ID_EX_Register_tb.dut);

        // Test sequence
        $display("==================== ID_EX Register Test START ====================\n");

        // reset
        reset = 1'b1;
        #30;
        reset = 1'b0;
        @(posedge clk);
        $display("Input now\n");
        $display("|     PC     |     PC+4     |   branch est  | jump | branch | CSR WE | RegF WE | ALUsrcA | ALUsrcB |");
        $display("|  %h  |   %h   |       %b       |   %b  |    %b   |    %b   |    %b    |    %b   |   %b   |", EX_pc, EX_pc_plus_4, EX_branch_estimation, EX_jump, EX_branch, EX_csr_write_enable, EX_register_write_enable, EX_alu_src_A_select, EX_alu_src_B_select);
        $display("| MEMread | MEMwrite | RF_WD select |  opcode  | funct3 |  funct7   |   raw_imm   |");
        $display("|    %b    |     %b    |      %b     |  %b |   %b  |  %b  |  %b  |", EX_memory_read, EX_memory_write, EX_register_file_write_data_select, EX_opcode, EX_funct3, EX_funct7, EX_raw_imm);
        $display("| Register RD1 | Register RD2 |   rs1   |     imm    | csr_read_data |  rd  |");
        $display("|   %h   |   %h   |  %b  |  %h  |   %h   | %b |\n", EX_read_data1, EX_read_data2, EX_rs1, EX_imm, EX_csr_read_data, EX_rd);
        #10;
        
        // Test 1
        @(negedge clk); 
        ID_pc = 64'h0000_0000;
        ID_pc_plus_4 = 64'h0000_0004;
        ID_branch_estimation = 1'b0;

        ID_jump = 1'b1;
        ID_branch = 1'b0;
        ID_alu_src_A_select = 2'b01;
        ID_alu_src_B_select = 2'b10;
        ID_memory_read = 1'b0;
        ID_memory_write = 1'b0;
        ID_register_file_write_data_select = 3'b001;
        ID_register_write_enable = 1'b0;
        ID_csr_write_enable = 1'b0;
        ID_opcode = 7'b0011000;
        ID_funct3 = 3'b010;
        ID_funct7 = 7'b0011110;
        ID_rd = 5'b00110;
        ID_raw_imm = 20'b0;
        ID_read_data1 = 64'hAAAA_AAAA_AAAA_AAAA;
        ID_read_data2 = 64'hBBBB_BBBB_BBBB_BBBB;
        ID_rs1 = 5'b01100;
        ID_imm = 64'h0000_0000_0000_0000;
        ID_csr_read_data = 64'h0000_0000_0000_0000;

        @(posedge clk); #1;
        $display("Test 1: Previous value should be output now\n");
        $display("|     PC     |     PC+4     |   branch est  | jump | branch | CSR WE | RegF WE | ALUsrcA | ALUsrcB |");
        $display("|  %h  |   %h   |       %b       |   %b  |    %b   |    %b   |    %b    |    %b   |   %b   |", EX_pc, EX_pc_plus_4, EX_branch_estimation, EX_jump, EX_branch, EX_csr_write_enable, EX_register_write_enable, EX_alu_src_A_select, EX_alu_src_B_select);
        $display("| MEMread | MEMwrite | RF_WD select |  opcode  | funct3 |  funct7   |   raw_imm   |");
        $display("|    %b    |     %b    |      %b     |  %b |   %b  |  %b  |  %b  |", EX_memory_read, EX_memory_write, EX_register_file_write_data_select, EX_opcode, EX_funct3, EX_funct7, EX_raw_imm);
        $display("| Register RD1 | Register RD2 |   rs1   |     imm    | csr_read_data |  rd  |");
        $display("|   %h   |   %h   |  %b  |  %h  |   %h   | %b |\n", EX_read_data1, EX_read_data2, EX_rs1, EX_imm, EX_csr_read_data, EX_rd);
        
        // Test 2@(posedge clk); #1;
        @(posedge clk); #1;
        $display("Test 2: No input(should be same)\n");
        $display("|     PC     |     PC+4     |   branch est  | jump | branch | CSR WE | RegF WE | ALUsrcA | ALUsrcB |");
        $display("|  %h  |   %h   |       %b       |   %b  |    %b   |    %b   |    %b    |    %b   |   %b   |", EX_pc, EX_pc_plus_4, EX_branch_estimation, EX_jump, EX_branch, EX_csr_write_enable, EX_register_write_enable, EX_alu_src_A_select, EX_alu_src_B_select);
        $display("| MEMread | MEMwrite | RF_WD select |  opcode  | funct3 |  funct7   |   raw_imm   |");
        $display("|    %b    |     %b    |      %b     |  %b |   %b  |  %b  |  %b  |", EX_memory_read, EX_memory_write, EX_register_file_write_data_select, EX_opcode, EX_funct3, EX_funct7, EX_raw_imm);
        $display("| Register RD1 | Register RD2 |   rs1   |     imm    | csr_read_data |  rd  |");
        $display("|   %h   |   %h   |  %b  |  %h  |   %h   | %b |\n", EX_read_data1, EX_read_data2, EX_rs1, EX_imm, EX_csr_read_data, EX_rd);

        // Test 3
        @(negedge clk); 
        ID_pc                         = 64'h0000_0000;
        ID_pc_plus_4                  = 64'h0000_0004;
        ID_branch_estimation          = 1'b0;

        ID_jump                       = 1'b0;
        ID_branch                     = 1'b0;
        ID_alu_src_A_select           = 2'b00;      // rs1
        ID_alu_src_B_select           = 3'b000;     // rs2
        ID_memory_read                = 1'b0;
        ID_memory_write               = 1'b0;
        ID_register_file_write_data_select = 3'b000; // ALU result
        ID_register_write_enable      = 1'b1;
        ID_csr_write_enable           = 1'b0;
        ID_opcode                     = 7'b0110011; // R-type
        ID_funct3                     = 3'b000;     // ADD
        ID_funct7                     = 7'b0000000; 
        ID_rd                         = 5'b01000;
        ID_raw_imm                    = 20'h000;
        ID_read_data1                 = 64'h0000_0000_0000_0005; 
        ID_read_data2                 = 64'h0000_0000_0000_000A;
        ID_rs1                        = 5'd5;
        ID_imm                        = 64'h0000_0000_0000_0000;
        ID_csr_read_data              = 64'h0000_0000_0000_0000;
        $display("Test 3-1: new input now(should be same) \n");
        $display("|     PC     |     PC+4     |   branch est  | jump | branch | CSR WE | RegF WE | ALUsrcA | ALUsrcB |");
        $display("|  %h  |   %h   |       %b       |   %b  |    %b   |    %b   |    %b    |    %b   |   %b   |", EX_pc, EX_pc_plus_4, EX_branch_estimation, EX_jump, EX_branch, EX_csr_write_enable, EX_register_write_enable, EX_alu_src_A_select, EX_alu_src_B_select);
        $display("| MEMread | MEMwrite | RF_WD select |  opcode  | funct3 |  funct7   |   raw_imm   |");
        $display("|    %b    |     %b    |      %b     |  %b |   %b  |  %b  |  %b  |", EX_memory_read, EX_memory_write, EX_register_file_write_data_select, EX_opcode, EX_funct3, EX_funct7, EX_raw_imm);
        $display("| Register RD1 | Register RD2 |   rs1   |     imm    | csr_read_data |  rd  |");
        $display("|   %h   |   %h   |  %b  |  %h  |   %h   | %b |\n", EX_read_data1, EX_read_data2, EX_rs1, EX_imm, EX_csr_read_data, EX_rd);

        @(posedge clk); #1;
        $display("Test 3-2: Test 3-1 input should be output now \n");
        $display("|     PC     |     PC+4     |   branch est  | jump | branch | CSR WE | RegF WE | ALUsrcA | ALUsrcB |");
        $display("|  %h  |   %h   |       %b       |   %b  |    %b   |    %b   |    %b    |    %b   |   %b   |", EX_pc, EX_pc_plus_4, EX_branch_estimation, EX_jump, EX_branch, EX_csr_write_enable, EX_register_write_enable, EX_alu_src_A_select, EX_alu_src_B_select);
        $display("| MEMread | MEMwrite | RF_WD select |  opcode  | funct3 |  funct7   |   raw_imm   |");
        $display("|    %b    |     %b    |      %b     |  %b |   %b  |  %b  |  %b  |", EX_memory_read, EX_memory_write, EX_register_file_write_data_select, EX_opcode, EX_funct3, EX_funct7, EX_raw_imm);
        $display("| Register RD1 | Register RD2 |   rs1   |     imm    | csr_read_data |  rd  |");
        $display("|   %h   |   %h   |  %b  |  %h  |   %h   | %b |\n", EX_read_data1, EX_read_data2, EX_rs1, EX_imm, EX_csr_read_data, EX_rd);

        flush = 1'b1; #10;
        flush = 1'b0;

        // Test 3
        $display("Test 4: Flushed (should be NOP and zero)\n");
        $display("|     PC     |     PC+4     |   branch est  | jump | branch | CSR WE | RegF WE | ALUsrcA | ALUsrcB |");
        $display("|  %h  |   %h   |       %b       |   %b  |    %b   |    %b   |    %b    |    %b   |   %b   |", EX_pc, EX_pc_plus_4, EX_branch_estimation, EX_jump, EX_branch, EX_csr_write_enable, EX_register_write_enable, EX_alu_src_A_select, EX_alu_src_B_select);
        $display("| MEMread | MEMwrite | RF_WD select |  opcode  | funct3 |  funct7   |   raw_imm   |");
        $display("|    %b    |     %b    |      %b     |  %b |   %b  |  %b  |  %b  |", EX_memory_read, EX_memory_write, EX_register_file_write_data_select, EX_opcode, EX_funct3, EX_funct7, EX_raw_imm);
        $display("| Register RD1 | Register RD2 |   rs1   |     imm    | csr_read_data |  rd  |");
        $display("|   %h   |   %h   |  %b  |  %h  |   %h   | %b |\n", EX_read_data1, EX_read_data2, EX_rs1, EX_imm, EX_csr_read_data, EX_rd);

        ID_pc                         = 64'h1000_1000;
        ID_pc_plus_4                  = 64'h1000_1004;
        ID_branch_estimation          = 1'b1;       // branch predicted taken

        ID_jump                       = 1'b0;
        ID_branch                     = 1'b1;
        ID_alu_src_A_select           = 2'b00;      // rs1 base
        ID_alu_src_B_select           = 3'b001;     // imm
        ID_memory_read                = 1'b1;
        ID_memory_write               = 1'b0;
        ID_register_file_write_data_select = 3'b001; // MEM data
        ID_register_write_enable = 1'b0;
        ID_csr_write_enable = 1'b1;
        ID_opcode                     = 7'b0000011; // I-type LOAD
        ID_funct3                     = 3'b010;     // LW
        ID_funct7                     = 7'b0000000;
        ID_rd                         = 5'b01111;
        ID_raw_imm                    = 20'h0F0;
        ID_read_data1                 = 64'h0000_0000_0000_0004; 
        ID_read_data2                 = 64'h0000_0000_0000_0000; // unused for load
        ID_rs1                        = 5'd2;
        ID_imm                        = 64'h0000_0000_0000_00F0;
        ID_csr_read_data              = 64'h0000_0000_0000_0000;
        $display("Test 5-1: Input begin (should be same)\n");
        $display("|     PC     |     PC+4     |   branch est  | jump | branch | CSR WE | RegF WE | ALUsrcA | ALUsrcB |");
        $display("|  %h  |   %h   |       %b       |   %b  |    %b   |    %b   |    %b    |    %b   |   %b   |", EX_pc, EX_pc_plus_4, EX_branch_estimation, EX_jump, EX_branch, EX_csr_write_enable, EX_register_write_enable, EX_alu_src_A_select, EX_alu_src_B_select);
        $display("| MEMread | MEMwrite | RF_WD select |  opcode  | funct3 |  funct7   |   raw_imm   |");
        $display("|    %b    |     %b    |      %b     |  %b |   %b  |  %b  |  %b  |", EX_memory_read, EX_memory_write, EX_register_file_write_data_select, EX_opcode, EX_funct3, EX_funct7, EX_raw_imm);
        $display("| Register RD1 | Register RD2 |   rs1   |     imm    | csr_read_data |  rd  |");
        $display("|   %h   |   %h   |  %b  |  %h  |   %h   | %b |\n", EX_read_data1, EX_read_data2, EX_rs1, EX_imm, EX_csr_read_data, EX_rd);
        #10;
        $display("Test 5-2: Test 5-1's input should be output now\n");
        $display("|     PC     |     PC+4     |   branch est  | jump | branch | CSR WE | RegF WE | ALUsrcA | ALUsrcB |");
        $display("|  %h  |   %h   |       %b       |   %b  |    %b   |    %b   |    %b    |    %b   |   %b   |", EX_pc, EX_pc_plus_4, EX_branch_estimation, EX_jump, EX_branch, EX_csr_write_enable, EX_register_write_enable, EX_alu_src_A_select, EX_alu_src_B_select);
        $display("| MEMread | MEMwrite | RF_WD select |  opcode  | funct3 |  funct7   |   raw_imm   |");
        $display("|    %b    |     %b    |      %b     |  %b |   %b  |  %b  |  %b  |", EX_memory_read, EX_memory_write, EX_register_file_write_data_select, EX_opcode, EX_funct3, EX_funct7, EX_raw_imm);
        $display("| Register RD1 | Register RD2 |   rs1   |     imm    | csr_read_data |  rd  |");
        $display("|   %h   |   %h   |  %b  |  %h  |   %h   | %b |\n", EX_read_data1, EX_read_data2, EX_rs1, EX_imm, EX_csr_read_data, EX_rd);

        $display("\n====================  ID_EX Register Test END  ====================");

        $stop;
    end

endmodule

testbenches/results/waveforms/ID_EX_Register_tb_result.vcd
$date
	Mon Dec 29 12:49:52 2025
$end
$version
	Icarus Verilog
$end
$timescale
	1ps
$end
$scope module ID_EX_Register_tb $end
$scope module dut $end
$var wire 1 ! ID_EX_stall $end
$var wire 2 " ID_alu_src_A_select [1:0] $end
$var wire 3 # ID_alu_src_B_select [2:0] $end
$var wire 1 $ ID_branch $end
$var wire 1 % ID_branch_estimation $end
$var wire 64 & ID_csr_read_data [63:0] $end
$var wire 1 ' ID_csr_write_enable $end
$var wire 3 ( ID_funct3 [2:0] $end
$var wire 7 ) ID_funct7 [6:0] $end
$var wire 64 * ID_imm [63:0] $end
$var wire 32 + ID_instruction [31:0] $end
$var wire 1 , ID_jump $end
$var wire 1 - ID_memory_read $end
$var wire 1 . ID_memory_write $end
$var wire 7 / ID_opcode [6:0] $end
$var wire 64 0 ID_pc [63:0] $end
$var wire 64 1 ID_pc_plus_4 [63:0] $end
$var wire 20 2 ID_raw_imm [19:0] $end
$var wire 5 3 ID_rd [4:0] $end
$var wire 64 4 ID_read_data1 [63:0] $end
$var wire 64 5 ID_read_data2 [63:0] $end
$var wire 3 6 ID_register_file_write_data_select [2:0] $end
$var wire 1 7 ID_register_write_enable $end
$var wire 5 8 ID_rs1 [4:0] $end
$var wire 5 9 ID_rs2 [4:0] $end
$var wire 1 : clk $end
$var wire 1 ; flush $end
$var wire 1 < reset $end
$var parameter 32 = XLEN $end
$var reg 2 > EX_alu_src_A_select [1:0] $end
$var reg 3 ? EX_alu_src_B_select [2:0] $end
$var reg 1 @ EX_branch $end
$var reg 1 A EX_branch_estimation $end
$var reg 64 B EX_csr_read_data [63:0] $end
$var reg 1 C EX_csr_write_enable $end
$var reg 3 D EX_funct3 [2:0] $end
$var reg 7 E EX_funct7 [6:0] $end
$var reg 64 F EX_imm [63:0] $end
$var reg 32 G EX_instruction [31:0] $end
$var reg 1 H EX_jump $end
$var reg 1 I EX_memory_read $end
$var reg 1 J EX_memory_write $end
$var reg 7 K EX_opcode [6:0] $end
$var reg 64 L EX_pc [63:0] $end
$var reg 64 M EX_pc_plus_4 [63:0] $end
$var reg 20 N EX_raw_imm [19:0] $end
$var reg 5 O EX_rd [4:0] $end
$var reg 64 P EX_read_data1 [63:0] $end
$var reg 64 Q EX_read_data2 [63:0] $end
$var reg 3 R EX_register_file_write_data_select [2:0] $end
$var reg 1 S EX_register_write_enable $end
$var reg 5 T EX_rs1 [4:0] $end
$var reg 5 U EX_rs2 [4:0] $end
$upscope $end
$upscope $end
$enddefinitions $end
$comment Show the parameter values. $end
$dumpall
b1000000 =
$end
#0
$dumpvars
b0 U
b0 T
0S
b0 R
b0 Q
b0 P
b0 O
b0 N
b0 M
b0 L
b0 K
0J
0I
0H
b10011 G
b0 F
b0 E
b0 D
0C
b0 B
0A
0@
b0 ?
b0 >
1<
0;
0:
bz 9
bx 8
x7
bx 6
bx 5
bx 4
bx 3
bx 2
bx 1
bx 0
bx /
x.
x-
x,
bz +
bx *
bx )
bx (
x'
bx &
x%
x$
bx #
bx "
0!
$end
#5000
1:
#10000
0:
#15000
1:
#20000
0:
#25000
1:
#30000
0:
0<
#35000
bx B
bx F
bz U
bx T
bx Q
bx P
bx N
bx O
bx E
bx D
bx K
bx ?
bx >
x@
xC
xS
bx R
xJ
xI
xH
bz G
xA
bx M
bx L
1:
#40000
0:
#45000
1:
#50000
b0 &
b0 *
b1100 8
b1011101110111011101110111011101110111011101110111011101110111011 5
b1010101010101010101010101010101010101010101010101010101010101010 4
b0 2
b110 3
b11110 )
b10 (
b11000 /
0'
07
b1 6
0.
0-
b10 #
b1 "
0$
1,
0%
b100 1
b0 0
0:
#55000
b0 B
b0 F
b1100 T
b1011101110111011101110111011101110111011101110111011101110111011 Q
b1010101010101010101010101010101010101010101010101010101010101010 P
b0 N
b110 O
b11110 E
b10 D
b11000 K
b10 ?
b1 >
0@
0C
0S
b1 R
0J
0I
1H
0A
b100 M
b0 L
1:
#60000
0:
#65000
1:
#70000
b101 8
b1010 5
b101 4
b1000 3
b0 )
b0 (
b110011 /
17
b0 6
b0 #
b0 "
0,
0:
#75000
b101 T
b1010 Q
b101 P
b1000 O
b0 E
b0 D
b110011 K
b0 ?
b0 >
1S
b0 R
0H
1:
#76000
1;
#80000
0:
#85000
b0 U
b0 T
b0 Q
b0 P
b0 O
b0 K
0S
b10011 G
b0 M
1:
#86000
b11110000 *
b10 8
b0 5
b100 4
b11110000 2
b1111 3
b10 (
b11 /
1'
07
b1 6
1-
b1 #
1$
1%
b10000000000000001000000000100 1
b10000000000000001000000000000 0
0;
#90000
0:
#95000
b11110000 F
bz U
b10 T
b100 P
b11110000 N
b1111 O
b10 D
b11 K
b1 ?
1@
1C
b1 R
1I
bz G
1A
b10000000000000001000000000100 M
b10000000000000001000000000000 L
1:
