modules/Immediate_Generator.v
`include "modules/headers/opcode.vh"

module ImmediateGenerator (
    input [19:0] raw_imm, 	// raw immediate value from Instruction Decoder
	input [6:0] opcode,		// opcode from Instruction Decoder
    output reg [63:0] imm	// sign-extension of the raw immediate value
);
	
	always @(*) begin
		case (opcode)
			`OPCODE_JALR, `OPCODE_LOAD, `OPCODE_ITYPE, `OPCODE_ITYPE_WORD, `OPCODE_FENCE, `OPCODE_ENVIRONMENT: begin // I-type
				imm = {{52{raw_imm[11]}}, raw_imm[11:0]};
			end
			`OPCODE_STORE: begin // S-Type
				imm = {{52{raw_imm[11]}}, raw_imm[11:0]};
			end
			`OPCODE_LUI, `OPCODE_AUIPC: begin // U-Type
				imm = {{32{raw_imm[19]}}, raw_imm, 12'b0};
			end
			`OPCODE_BRANCH: begin // B-Type
				imm = {{51{raw_imm[11]}}, raw_imm[11:0], 1'b0};
			end
			`OPCODE_JAL: begin // J-Type
				imm = {{43{raw_imm[19]}}, raw_imm[19:0], 1'b0};
			end
			default: begin
				imm = 64'b0;
			end
        endcase
	end
	
endmodule

testbenches/Immediate_Generator_tb.v
`timescale 1ns/1ps

`include "modules/headers/opcode.vh"

module ImmediateGenerator_tb;
    reg [19:0] raw_imm;
	reg [6:0] opcode;
    wire [63:0] imm;

    ImmediateGenerator dut (
        .raw_imm(raw_imm),
		.opcode(opcode),
		.imm(imm)
    );

    initial begin
        $dumpfile("testbenches/results/waveforms/Immediate_Generator_tb_result.vcd");
        $dumpvars(0, dut);

        // Test sequence
        $display("==================== Immediate Generator Test START ====================");

        raw_imm = 20'b0;
		opcode = 7'b0;

        // Test 1: I-type
		$display("\nI-type: ");
		
        raw_imm = 20'd1972;
		opcode = `OPCODE_JALR;

        #1;
        $display("raw_imm: %h (%d), imm: %h (%d)", raw_imm[11:0], $signed(raw_imm[11:0]), imm, $signed(imm));
		
        raw_imm = -20'd1121;
		opcode = `OPCODE_LOAD;

        #1;
        $display("raw_imm: %h (%d), imm: %h (%d)", raw_imm[11:0], $signed(raw_imm[11:0]), imm, $signed(imm));
		
		raw_imm = 20'd310;
		opcode = `OPCODE_ITYPE;

        #1;
        $display("raw_imm: %h (%d), imm: %h (%d)", raw_imm[11:0], $signed(raw_imm[11:0]), imm, $signed(imm));

        raw_imm = 20'd804;
		opcode = `OPCODE_ITYPE_WORD;

        #1;
        $display("raw_imm: %h (%d), imm: %h (%d)", raw_imm[11:0], $signed(raw_imm[11:0]), imm, $signed(imm));
		
		raw_imm = 20'd0;
		opcode = `OPCODE_FENCE;

        #1;
        $display("raw_imm: %h (%d), imm: %h (%d)", raw_imm[11:0], $signed(raw_imm[11:0]), imm, $signed(imm));
		
		raw_imm = -20'd2025;
		opcode = `OPCODE_ENVIRONMENT;

        #1;
        $display("raw_imm: %h (%d), imm: %h (%d)", raw_imm[11:0], $signed(raw_imm[11:0]), imm, $signed(imm));

        // Test 2: S-type
		$display("\nS-type: ");
		
		raw_imm = 20'd1972;
		opcode = `OPCODE_STORE;

        #1;
        $display("raw_imm: %h (%d), imm: %h (%d)", raw_imm[11:0], $signed(raw_imm[11:0]), imm, $signed(imm));
		
		raw_imm = -20'd1121;
		opcode = `OPCODE_STORE;

        #1;
		$display("raw_imm: %h (%d), imm: %h (%d)", raw_imm[11:0], $signed(raw_imm[11:0]), imm, $signed(imm));

        // Test 3: U-type
		$display("\nU-type: ");
		
		raw_imm = 20'h0BEEF;
		opcode = `OPCODE_LUI;

        #1;
        $display("raw_imm: %h, imm: %h", raw_imm, imm);
		
		raw_imm = 20'hDBEEF;
		opcode = `OPCODE_AUIPC;

        #1;
        $display("raw_imm: %h, imm: %h", raw_imm, imm);
		
		// Test 4: B-type
		$display("\nB-type: ");
		
		raw_imm = 20'd1972;
		opcode = `OPCODE_BRANCH;

        #1;
        $display("raw_imm: %h (%d), imm: %h (%d)", raw_imm[11:0], $signed(raw_imm[11:0]), imm, $signed(imm));
		
		raw_imm = -20'd1121;

        #1;
		$display("raw_imm: %h (%d), imm: %h (%d)", raw_imm[11:0], $signed(raw_imm[11:0]), imm, $signed(imm));

        // Test 5: J-type
		$display("\nJ-type: ");
		
		raw_imm = 20'd1972;
		opcode = `OPCODE_JAL;

        #1;
        $display("raw_imm: %h (%d), imm: %h (%d)", raw_imm[19:0], $signed(raw_imm[19:0]), imm, $signed(imm));
		
		raw_imm = -20'd1121;

        #1;
        $display("raw_imm: %h (%d), imm: %h (%d)", raw_imm[19:0], $signed(raw_imm[19:0]), imm, $signed(imm));

        // Test 6: R-type (which should return 0)
		$display("\nR-type (which should return 0): ");
		
		raw_imm = 20'd1972;
		opcode = `OPCODE_RTYPE;

        #1;
        $display("raw_imm: %h (%d), imm: %h (%d)", raw_imm[19:0], $signed(raw_imm[19:0]), imm, $signed(imm));
		
		raw_imm = -20'd1121;
        opcode = `OPCODE_RTYPE_WORD;

        #1;
        $display("raw_imm: %h (%d), imm: %h (%d)", raw_imm[19:0], $signed(raw_imm[19:0]), imm, $signed(imm));

        $display("\n====================  Immediate Generator Test END  ====================");

        $stop;
    end

endmodule

testbenches/results/waveforms/Immediate_Generator_tb_result.vcd
$date
	Mon Jul 14 14:37:26 2025
$end
$version
	Icarus Verilog
$end
$timescale
	1ps
$end
$scope module ImmediateGenerator_tb $end
$scope module dut $end
$var wire 7 ! opcode [6:0] $end
$var wire 20 " raw_imm [19:0] $end
$var reg 64 # imm [63:0] $end
$upscope $end
$upscope $end
$enddefinitions $end
$comment Show the parameter values. $end
$dumpall
$end
#0
$dumpvars
b11110110100 #
b11110110100 "
b1100111 !
$end
#1000
b1111111111111111111111111111111111111111111111111111101110011111 #
b11 !
b11111111101110011111 "
#2000
b100110110 #
b10011 !
b100110110 "
#3000
b1100100100 #
b11011 !
b1100100100 "
#4000
b0 #
b1111 !
b0 "
#5000
b1111111111111111111111111111111111111111111111111111100000010111 #
b1110011 !
b11111111100000010111 "
#6000
b11110110100 #
b100011 !
b11110110100 "
#7000
b1111111111111111111111111111111111111111111111111111101110011111 #
b11111111101110011111 "
#8000
b1011111011101111000000000000 #
b110111 !
b1011111011101111 "
#9000
b1111111111111111111111111111111111011011111011101111000000000000 #
b10111 !
b11011011111011101111 "
#10000
b111101101000 #
b1100011 !
b11110110100 "
#11000
b1111111111111111111111111111111111111111111111111111011100111110 #
b11111111101110011111 "
#12000
b111101101000 #
b1101111 !
b11110110100 "
#13000
b1111111111111111111111111111111111111111111111111111011100111110 #
b11111111101110011111 "
#14000
b0 #
b110011 !
b11110110100 "
#15000
b111011 !
b11111111101110011111 "
