modules/MEM_WB_Register.v
module MEM_WB_Register #(
    parameter XLEN = 64
)(
    // pipeline register control signals
    input wire clk,
    input wire reset,
    input wire MEM_WB_stall,
    input wire flush,

    // signals from EX/MEM register
    input wire [XLEN-1:0] MEM_pc,
    input wire [XLEN-1:0] MEM_pc_plus_4,
    input wire [31:0] MEM_instruction,

    input wire [2:0] MEM_register_file_write_data_select,
    input wire [XLEN-1:0] MEM_imm,
    input wire [19:0] MEM_raw_imm,
    input wire [XLEN-1:0] MEM_csr_read_data,
    input wire [XLEN-1:0] MEM_alu_result,
    input wire MEM_register_write_enable,
    input wire MEM_csr_write_enable,
    input wire [4:0] MEM_rs1,
    input wire [4:0] MEM_rd,
    input wire [6:0] MEM_opcode,

    // signals from MEM phase
    input wire [XLEN-1:0] MEM_byte_enable_logic_register_file_write_data,

    // signals to MEM register
    output reg [XLEN-1:0] WB_pc,
    output reg [XLEN-1:0] WB_pc_plus_4,
    output reg [31:0] WB_instruction,

    output reg [2:0] WB_register_file_write_data_select,
    output reg [XLEN-1:0] WB_imm,
    output reg [19:0] WB_raw_imm,
    output reg [XLEN-1:0] WB_csr_read_data,
    output reg [XLEN-1:0] WB_alu_result,
    output reg WB_register_write_enable,
    output reg WB_csr_write_enable,
    output reg [4:0] WB_rs1,
    output reg [4:0] WB_rd,
    output reg [6:0] WB_opcode,

    output reg [XLEN-1:0] WB_byte_enable_logic_register_file_write_data
);

always @(posedge clk or posedge reset) begin
    if (reset) begin
        WB_pc <= {XLEN{1'b0}};
        WB_pc_plus_4 <= {XLEN{1'b0}};
        WB_instruction <= 32'h0000_0013; // ADDI x0, x0, 0 = RISC-V NOP, HINT

        WB_register_file_write_data_select <= 3'b0;
        WB_imm <= {XLEN{1'b0}};
        WB_raw_imm <= 20'b0;
        WB_csr_read_data <= {XLEN{1'b0}};
        WB_alu_result <= {XLEN{1'b0}};
        WB_register_write_enable <= 1'b0;
        WB_csr_write_enable <= 1'b0;
        WB_rs1 <= 5'b0;
        WB_rd <= 5'b0;
        WB_opcode <= 7'b0;
        
        WB_byte_enable_logic_register_file_write_data <= {XLEN{1'b0}};
    end 
    else begin
        if (flush) begin
            WB_pc <= {XLEN{1'b0}};
            WB_pc_plus_4 <= {XLEN{1'b0}};
            WB_instruction <= 32'h0000_0013; // ADDI x0, x0, 0 = RISC-V NOP, HINT

            WB_register_file_write_data_select <= 3'b0;
            WB_imm <= {XLEN{1'b0}};
            WB_raw_imm <= 20'b0;
            WB_csr_read_data <= {XLEN{1'b0}};
            WB_alu_result <= {XLEN{1'b0}};
            WB_register_write_enable <= 1'b0;
            WB_csr_write_enable <= 1'b0;
            WB_rs1 <= 5'b0;
            WB_rd <= 5'b0;
            WB_opcode <= 7'b0;
            
            WB_byte_enable_logic_register_file_write_data <= {XLEN{1'b0}};
        end 
        else if (!MEM_WB_stall) begin
            WB_pc <= MEM_pc;
            WB_pc_plus_4 <= MEM_pc_plus_4;
            WB_instruction <= MEM_instruction;

            WB_register_file_write_data_select <= MEM_register_file_write_data_select;
            WB_imm <= MEM_imm;
            WB_raw_imm <= MEM_raw_imm;
            WB_csr_read_data <= MEM_csr_read_data;
            WB_alu_result <= MEM_alu_result;
            WB_register_write_enable <= MEM_register_write_enable;
            WB_csr_write_enable <= MEM_csr_write_enable;
            WB_rs1 <= MEM_rs1;
            WB_rd <= MEM_rd;
            WB_opcode <= MEM_opcode;
            
            WB_byte_enable_logic_register_file_write_data <= MEM_byte_enable_logic_register_file_write_data;
        end 
    end 
end

endmodule

testbenches/MEM_WB_Register_tb.v
`timescale 1ns/1ps

module MEM_WB_Register_tb;
    localparam XLEN = 64;

    reg clk = 0;
    reg reset = 0;
    reg MEM_WB_stall = 0;
    reg flush = 0;

    // signals from EX/MEM register
    reg [XLEN-1:0] MEM_pc;
    reg [XLEN-1:0] MEM_pc_plus_4;
    reg [31:0] MEM_instruction;
    reg [2:0] MEM_register_file_write_data_select;
    reg [XLEN-1:0] MEM_imm;
    reg [19:0] MEM_raw_imm;
    reg [XLEN-1:0] MEM_csr_read_data;
    reg [XLEN-1:0] MEM_alu_result;
    reg MEM_register_write_enable;
    reg MEM_csr_write_enable;
    reg [4:0] MEM_rs1;
    reg [4:0] MEM_rd;
    reg [6:0] MEM_opcode;

    // signals from MEM phase
    reg [XLEN-1:0] MEM_byte_enable_logic_register_file_write_data;

    // outputs
    wire [XLEN-1:0] WB_pc;
    wire [XLEN-1:0] WB_pc_plus_4;
    wire [31:0] WB_instruction;
    wire [2:0] WB_register_file_write_data_select;
    wire [XLEN-1:0] WB_imm;
    wire [19:0] WB_raw_imm;
    wire [XLEN-1:0] WB_csr_read_data;
    wire [XLEN-1:0] WB_alu_result;
    wire WB_register_write_enable;
    wire WB_csr_write_enable;
    wire [4:0] WB_rs1;
    wire [4:0] WB_rd;
    wire [6:0] WB_opcode;
    wire [XLEN-1:0] WB_byte_enable_logic_register_file_write_data;

    // test result tracking
    integer pass_count = 0;
    integer fail_count = 0;

    MEM_WB_Register #(.XLEN(XLEN)) mem_wb_register (
        .clk(clk),
        .reset(reset),
        .MEM_WB_stall(MEM_WB_stall),
        .flush(flush),

        .MEM_pc(MEM_pc),
        .MEM_pc_plus_4(MEM_pc_plus_4),
        .MEM_instruction(MEM_instruction),
        .MEM_register_file_write_data_select(MEM_register_file_write_data_select),
        .MEM_imm(MEM_imm),
        .MEM_raw_imm(MEM_raw_imm),
        .MEM_csr_read_data(MEM_csr_read_data),
        .MEM_alu_result(MEM_alu_result),
        .MEM_register_write_enable(MEM_register_write_enable),
        .MEM_csr_write_enable(MEM_csr_write_enable),
        .MEM_rs1(MEM_rs1),
        .MEM_rd(MEM_rd),
        .MEM_opcode(MEM_opcode),
        .MEM_byte_enable_logic_register_file_write_data(MEM_byte_enable_logic_register_file_write_data),

        .WB_pc(WB_pc),
        .WB_pc_plus_4(WB_pc_plus_4),
        .WB_instruction(WB_instruction),
        .WB_register_file_write_data_select(WB_register_file_write_data_select),
        .WB_imm(WB_imm),
        .WB_raw_imm(WB_raw_imm),
        .WB_csr_read_data(WB_csr_read_data),
        .WB_alu_result(WB_alu_result),
        .WB_register_write_enable(WB_register_write_enable),
        .WB_csr_write_enable(WB_csr_write_enable),
        .WB_rs1(WB_rs1),
        .WB_rd(WB_rd),
        .WB_opcode(WB_opcode),
        .WB_byte_enable_logic_register_file_write_data(WB_byte_enable_logic_register_file_write_data)
    );

    always #5 clk = ~clk;

    // task for checking and displaying result
    task check;
        input [255:0] name;
        input [XLEN-1:0] expected;
        input [XLEN-1:0] actual;
        begin
            if (expected === actual) begin
                $display("[PASS] %0s | Expected: %h | Actual: %h", name, expected, actual);
                pass_count = pass_count + 1;
            end else begin
                $display("[FAIL] %0s | Expected: %h | Actual: %h", name, expected, actual);
                fail_count = fail_count + 1;
            end
        end
    endtask

    initial begin
        $dumpfile("testbenches/results/waveforms/MEM_WB_Register_tb_result.vcd");
        $dumpvars(0, MEM_WB_Register_tb.mem_wb_register);

        $display("\nMEM_WB_Register Test START\n");

        // initialize inputs
        MEM_pc = 0;
        MEM_pc_plus_4 = 0;
        MEM_instruction = 32'h0000_0013;
        MEM_register_file_write_data_select = 0;
        MEM_imm = 0;
        MEM_raw_imm = 0;
        MEM_csr_read_data = 0;
        MEM_alu_result = 0;
        MEM_register_write_enable = 0;
        MEM_csr_write_enable = 0;
        MEM_rs1 = 0;
        MEM_rd = 0;
        MEM_opcode = 0;
        MEM_byte_enable_logic_register_file_write_data = 0;

        // reset
        reset = 1'b1;
        #30;
        reset = 1'b0;
        @(posedge clk); #1;

        $display("Test 1: After Reset (should be NOP and zero)");
        $display("|       PC       |     PC+4     |  instruction | RF_WD_sel | CSR_WE | Reg_WE |");
        $display("| %h | %h |   %h   |    %b    |   %b    |   %b    |", WB_pc, WB_pc_plus_4, WB_instruction, WB_register_file_write_data_select, WB_csr_write_enable, WB_register_write_enable);
        $display("|     BERF_WD      |       imm      |  csr_read_data |   ALU result   | rs1 |  rd | opcode |");
        $display("| %h | %h | %h | %h | %b | %b | %b |", WB_byte_enable_logic_register_file_write_data, WB_imm, WB_csr_read_data, WB_alu_result, WB_rs1, WB_rd, WB_opcode);
        check("WB_pc", 64'h0, WB_pc);
        check("WB_pc_plus_4", 64'h0, WB_pc_plus_4);
        check("WB_instruction", 64'h0000_0013, {32'b0, WB_instruction});
        check("WB_alu_result", 64'h0, WB_alu_result);
        check("WB_register_write_enable", 64'h0, {63'b0, WB_register_write_enable});
        check("WB_rd", 64'h0, {59'b0, WB_rd});
        $display("");

        // Test 2: Normal data transfer
        @(negedge clk);
        MEM_pc                           = 64'h0000_0000_0000_0000;
        MEM_pc_plus_4                    = 64'h0000_0000_0000_0004;
        MEM_instruction                  = 32'h0062_8533;           // ADD x10, x5, x6
        MEM_register_file_write_data_select = 3'b010;               // ALU result -> Register File
        MEM_imm                          = 64'h0000_0000_0000_0000;
        MEM_raw_imm                      = 20'h00000;
        MEM_csr_read_data                = 64'h0000_0000_0000_0000;
        MEM_alu_result                   = 64'h0000_0000_0000_000B; // ALU result = 11
        MEM_register_write_enable        = 1'b1;                    // Register Write Enable
        MEM_csr_write_enable             = 1'b0;
        MEM_rs1                          = 5'd5;
        MEM_rd                           = 5'd10;
        MEM_opcode                       = 7'b0110011;              // R-type
        MEM_byte_enable_logic_register_file_write_data = 64'h0000_0000_0000_000A;

        @(posedge clk); #1;
        $display("Test 2: Normal data transfer");
        $display("|       PC       |     PC+4     |  instruction | RF_WD_sel | CSR_WE | Reg_WE |");
        $display("| %h | %h |   %h   |    %b    |   %b    |   %b    |", WB_pc, WB_pc_plus_4, WB_instruction, WB_register_file_write_data_select, WB_csr_write_enable, WB_register_write_enable);
        $display("|     BERF_WD      |       imm      |  csr_read_data |   ALU result   | rs1 |  rd | opcode |");
        $display("| %h | %h | %h | %h | %b | %b | %b |", WB_byte_enable_logic_register_file_write_data, WB_imm, WB_csr_read_data, WB_alu_result, WB_rs1, WB_rd, WB_opcode);
        check("WB_pc", 64'h0000_0000_0000_0000, WB_pc);
        check("WB_pc_plus_4", 64'h0000_0000_0000_0004, WB_pc_plus_4);
        check("WB_instruction", 64'h0062_8533, {32'b0, WB_instruction});
        check("WB_alu_result", 64'h0000_0000_0000_000B, WB_alu_result);
        check("WB_register_write_enable", 64'h1, {63'b0, WB_register_write_enable});
        check("WB_rd", 64'd10, {59'b0, WB_rd});
        check("WB_opcode", 64'b0110011, {57'b0, WB_opcode});
        $display("");

        // Test 3: Stall behavior (output should hold previous value)
        @(negedge clk);
        MEM_WB_stall = 1'b1;
        MEM_pc                           = 64'hFFFF_FFFF_FFFF_FFFF; // new value (should NOT be latched)
        MEM_pc_plus_4                    = 64'hFFFF_FFFF_FFFF_FFFF;
        MEM_instruction                  = 32'hFFFF_FFFF;
        MEM_alu_result                   = 64'hFFFF_FFFF_FFFF_FFFF;
        MEM_rd                           = 5'd31;

        @(posedge clk); #1;
        $display("Test 3: Stall behavior (should hold previous values)");
        $display("|       PC       |     PC+4     |  instruction | RF_WD_sel | CSR_WE | Reg_WE |");
        $display("| %h | %h |   %h   |    %b    |   %b    |   %b    |", WB_pc, WB_pc_plus_4, WB_instruction, WB_register_file_write_data_select, WB_csr_write_enable, WB_register_write_enable);
        $display("|     BERF_WD      |       imm      |  csr_read_data |   ALU result   | rs1 |  rd | opcode |");
        $display("| %h | %h | %h | %h | %b | %b | %b |", WB_byte_enable_logic_register_file_write_data, WB_imm, WB_csr_read_data, WB_alu_result, WB_rs1, WB_rd, WB_opcode);
        check("WB_pc (stalled)", 64'h0000_0000_0000_0000, WB_pc);
        check("WB_pc_plus_4 (stalled)", 64'h0000_0000_0000_0004, WB_pc_plus_4);
        check("WB_instruction (stalled)", 64'h0062_8533, {32'b0, WB_instruction});
        check("WB_alu_result (stalled)", 64'h0000_0000_0000_000B, WB_alu_result);
        check("WB_rd (stalled)", 64'd10, {59'b0, WB_rd});
        MEM_WB_stall = 1'b0;
        $display("");

        // Test 4: New data after stall released
        @(negedge clk);
        MEM_pc                           = 64'h0000_0000_0000_0004;
        MEM_pc_plus_4                    = 64'h0000_0000_0000_0008;
        MEM_instruction                  = 32'h0045_A503;           // LW x10, 4(x11)
        MEM_register_file_write_data_select = 3'b001;               // LOAD -> Register File
        MEM_imm                          = 64'h0000_0000_0000_0004;
        MEM_raw_imm                      = 20'h00004;
        MEM_csr_read_data                = 64'h0000_0000_0000_0000;
        MEM_alu_result                   = 64'h0000_0000_1000_0020; // address
        MEM_register_write_enable        = 1'b1;
        MEM_csr_write_enable             = 1'b0;
        MEM_rs1                          = 5'd11;
        MEM_rd                           = 5'd10;
        MEM_opcode                       = 7'b0000011;              // LOAD
        MEM_byte_enable_logic_register_file_write_data = 64'h0000_0000_DEAD_BEEF;

        @(posedge clk); #1;
        $display("Test 4: New data after stall released");
        $display("|       PC       |     PC+4     |  instruction | RF_WD_sel | CSR_WE | Reg_WE |");
        $display("| %h | %h |   %h   |    %b    |   %b    |   %b    |", WB_pc, WB_pc_plus_4, WB_instruction, WB_register_file_write_data_select, WB_csr_write_enable, WB_register_write_enable);
        $display("|     BERF_WD      |       imm      |  csr_read_data |   ALU result   | rs1 |  rd | opcode |");
        $display("| %h | %h | %h | %h | %b | %b | %b |", WB_byte_enable_logic_register_file_write_data, WB_imm, WB_csr_read_data, WB_alu_result, WB_rs1, WB_rd, WB_opcode);
        check("WB_pc", 64'h0000_0000_0000_0004, WB_pc);
        check("WB_pc_plus_4", 64'h0000_0000_0000_0008, WB_pc_plus_4);
        check("WB_instruction", 64'h0045_A503, {32'b0, WB_instruction});
        check("WB_alu_result", 64'h0000_0000_1000_0020, WB_alu_result);
        check("WB_byte_enable_logic_register_file_write_data", 64'h0000_0000_DEAD_BEEF, WB_byte_enable_logic_register_file_write_data);
        check("WB_rs1", 64'd11, {59'b0, WB_rs1});
        check("WB_opcode", 64'b0000011, {57'b0, WB_opcode});
        $display("");

        // Test 5: Flush behavior
        @(negedge clk);
        MEM_pc                           = 64'h0000_0000_0000_0008;
        MEM_pc_plus_4                    = 64'h0000_0000_0000_000C;
        MEM_instruction                  = 32'hCAFE_BABE;
        MEM_alu_result                   = 64'hABCD_1234_5678_9ABC;
        MEM_register_write_enable        = 1'b1;
        MEM_csr_write_enable             = 1'b1;
        MEM_rd                           = 5'd20;
        flush = 1'b1;

        @(posedge clk); #1;
        flush = 1'b0;
        $display("Test 5: Flush behavior (should be NOP and zero)");
        $display("|       PC       |     PC+4     |  instruction | RF_WD_sel | CSR_WE | Reg_WE |");
        $display("| %h | %h |   %h   |    %b    |   %b    |   %b    |", WB_pc, WB_pc_plus_4, WB_instruction, WB_register_file_write_data_select, WB_csr_write_enable, WB_register_write_enable);
        $display("|     BERF_WD      |       imm      |  csr_read_data |   ALU result   | rs1 |  rd | opcode |");
        $display("| %h | %h | %h | %h | %b | %b | %b |", WB_byte_enable_logic_register_file_write_data, WB_imm, WB_csr_read_data, WB_alu_result, WB_rs1, WB_rd, WB_opcode);
        check("WB_pc (flushed)", 64'h0, WB_pc);
        check("WB_pc_plus_4 (flushed)", 64'h0, WB_pc_plus_4);
        check("WB_instruction (flushed)", 64'h0000_0013, {32'b0, WB_instruction});
        check("WB_alu_result (flushed)", 64'h0, WB_alu_result);
        check("WB_register_write_enable (flushed)", 64'h0, {63'b0, WB_register_write_enable});
        check("WB_csr_write_enable (flushed)", 64'h0, {63'b0, WB_csr_write_enable});
        check("WB_rd (flushed)", 64'h0, {59'b0, WB_rd});
        $display("");

        // Test 6: CSR instruction
        @(negedge clk);
        MEM_pc                           = 64'h0000_0000_0000_000C;
        MEM_pc_plus_4                    = 64'h0000_0000_0000_0010;
        MEM_instruction                  = 32'hF11_02_573;           // CSRRS x10, mvendorid, x0
        MEM_register_file_write_data_select = 3'b011;                // CSR -> Register File
        MEM_imm                          = 64'h0000_0000_0000_0000;
        MEM_raw_imm                      = 20'hF1102;
        MEM_csr_read_data                = 64'h0000_0000_5256_4B43;  // mvendorid
        MEM_alu_result                   = 64'h0000_0000_0000_0000;
        MEM_register_write_enable        = 1'b1;
        MEM_csr_write_enable             = 1'b0;
        MEM_rs1                          = 5'd0;
        MEM_rd                           = 5'd10;
        MEM_opcode                       = 7'b1110011;               // ENVIRONMENT
        MEM_byte_enable_logic_register_file_write_data = 64'h0000_0000_5256_4B43;

        @(posedge clk); #1;
        $display("Test 6: CSR instruction");
        $display("|       PC       |     PC+4     |  instruction | RF_WD_sel | CSR_WE | Reg_WE |");
        $display("| %h | %h |   %h   |    %b    |   %b    |   %b    |", WB_pc, WB_pc_plus_4, WB_instruction, WB_register_file_write_data_select, WB_csr_write_enable, WB_register_write_enable);
        $display("|     BERF_WD      |       imm      |  csr_read_data |   ALU result   | rs1 |  rd | opcode |");
        $display("| %h | %h | %h | %h | %b | %b | %b |", WB_byte_enable_logic_register_file_write_data, WB_imm, WB_csr_read_data, WB_alu_result, WB_rs1, WB_rd, WB_opcode);
        check("WB_csr_read_data", 64'h0000_0000_5256_4B43, WB_csr_read_data);
        check("WB_raw_imm", 64'hF1102, {44'b0, WB_raw_imm});
        check("WB_opcode", 64'b1110011, {57'b0, WB_opcode});
        $display("");

        // Test 7: Flush priority over stall
        @(negedge clk);
        MEM_WB_stall = 1'b1;
        flush = 1'b1;
        MEM_pc                           = 64'h1234_5678_9ABC_DEF0;
        MEM_alu_result                   = 64'hFEDC_BA98_7654_3210;

        @(posedge clk); #1;
        MEM_WB_stall = 1'b0;
        flush = 1'b0;
        $display("Test 7: Flush priority over stall (flush should win)");
        $display("|       PC       |     PC+4     |  instruction | RF_WD_sel | CSR_WE | Reg_WE |");
        $display("| %h | %h |   %h   |    %b    |   %b    |   %b    |", WB_pc, WB_pc_plus_4, WB_instruction, WB_register_file_write_data_select, WB_csr_write_enable, WB_register_write_enable);
        check("WB_pc (flush priority)", 64'h0, WB_pc);
        check("WB_instruction (flush priority)", 64'h0000_0013, {32'b0, WB_instruction});
        check("WB_alu_result (flush priority)", 64'h0, WB_alu_result);
        $display("");

        // Summary
        $display("Test Summary: PASS = %0d, FAIL = %0d", pass_count, fail_count);
        if (fail_count == 0)
            $display("All tests PASSED!\n");
        else
            $display("Some tests FAILED!\n");

        $display("MEM_WB_Register Test END\n");
        $finish;
    end

endmodule

testbenches/results/waveforms/MEM_WB_Register_tb_result.vcd
$date
	Sat Jan 03 01:52:32 2026
$end
$version
	Icarus Verilog
$end
$timescale
	1ps
$end
$scope module MEM_WB_Register_tb $end
$scope module mem_wb_register $end
$var wire 1 ! MEM_WB_stall $end
$var wire 64 " MEM_alu_result [63:0] $end
$var wire 64 # MEM_byte_enable_logic_register_file_write_data [63:0] $end
$var wire 64 $ MEM_csr_read_data [63:0] $end
$var wire 1 % MEM_csr_write_enable $end
$var wire 64 & MEM_imm [63:0] $end
$var wire 32 ' MEM_instruction [31:0] $end
$var wire 7 ( MEM_opcode [6:0] $end
$var wire 64 ) MEM_pc [63:0] $end
$var wire 64 * MEM_pc_plus_4 [63:0] $end
$var wire 20 + MEM_raw_imm [19:0] $end
$var wire 5 , MEM_rd [4:0] $end
$var wire 3 - MEM_register_file_write_data_select [2:0] $end
$var wire 1 . MEM_register_write_enable $end
$var wire 5 / MEM_rs1 [4:0] $end
$var wire 1 0 clk $end
$var wire 1 1 flush $end
$var wire 1 2 reset $end
$var parameter 32 3 XLEN $end
$var reg 64 4 WB_alu_result [63:0] $end
$var reg 64 5 WB_byte_enable_logic_register_file_write_data [63:0] $end
$var reg 64 6 WB_csr_read_data [63:0] $end
$var reg 1 7 WB_csr_write_enable $end
$var reg 64 8 WB_imm [63:0] $end
$var reg 32 9 WB_instruction [31:0] $end
$var reg 7 : WB_opcode [6:0] $end
$var reg 64 ; WB_pc [63:0] $end
$var reg 64 < WB_pc_plus_4 [63:0] $end
$var reg 20 = WB_raw_imm [19:0] $end
$var reg 5 > WB_rd [4:0] $end
$var reg 3 ? WB_register_file_write_data_select [2:0] $end
$var reg 1 @ WB_register_write_enable $end
$var reg 5 A WB_rs1 [4:0] $end
$upscope $end
$upscope $end
$enddefinitions $end
$comment Show the parameter values. $end
$dumpall
b1000000 3
$end
#0
$dumpvars
b0 A
0@
b0 ?
b0 >
b0 =
b0 <
b0 ;
b0 :
b10011 9
b0 8
07
b0 6
b0 5
b0 4
12
01
00
b0 /
0.
b0 -
b0 ,
b0 +
b0 *
b0 )
b0 (
b10011 '
b0 &
0%
b0 $
b0 #
b0 "
0!
$end
#5000
10
#10000
00
#15000
10
#20000
00
#25000
10
#30000
00
02
#35000
10
#40000
b1010 #
b110011 (
b1010 ,
b101 /
1.
b1011 "
b10 -
b11000101000010100110011 '
b100 *
00
#45000
b1010 5
b110011 :
b1010 >
b101 A
1@
b1011 4
b10 ?
b11000101000010100110011 9
b100 <
10
#50000
b11111 ,
b1111111111111111111111111111111111111111111111111111111111111111 "
b11111111111111111111111111111111 '
b1111111111111111111111111111111111111111111111111111111111111111 *
b1111111111111111111111111111111111111111111111111111111111111111 )
1!
00
#55000
10
#56000
0!
#60000
b11011110101011011011111011101111 #
b11 (
b1010 ,
b1011 /
b10000000000000000000000100000 "
b100 +
b100 &
b1 -
b10001011010010100000011 '
b1000 *
b100 )
00
#65000
b11011110101011011011111011101111 5
b11 :
b1011 A
b10000000000000000000000100000 4
b100 =
b100 8
b1 ?
b10001011010010100000011 9
b1000 <
b100 ;
10
#70000
11
b10100 ,
1%
b1010101111001101000100100011010001010110011110001001101010111100 "
b11001010111111101011101010111110 '
b1100 *
b1000 )
00
#75000
b0 5
b0 :
b0 >
b0 A
0@
b0 4
b0 =
b0 8
b0 ?
b10011 9
b0 <
b0 ;
10
#76000
01
#80000
b1010010010101100100101101000011 #
b1110011 (
b1010 ,
b0 /
0%
b0 "
b1010010010101100100101101000011 $
b11110001000100000010 +
b0 &
b11 -
b11110001000100000010010101110011 '
b10000 *
b1100 )
00
#85000
b1010010010101100100101101000011 5
b1110011 :
b1010 >
1@
b1010010010101100100101101000011 6
b11110001000100000010 =
b11 ?
b11110001000100000010010101110011 9
b10000 <
b1100 ;
10
#90000
b1111111011011100101110101001100001110110010101000011001000010000 "
b1001000110100010101100111100010011010101111001101111011110000 )
11
1!
00
#95000
b0 5
b0 :
b0 >
0@
b0 6
b0 =
b0 ?
b10011 9
b0 <
b0 ;
10
#96000
01
0!
