modules/Program_Counter.v
module ProgramCounter #(
    parameter XLEN = 64
)(
    input clk,
    input reset,
    input [XLEN-1:0] next_pc,
    output reg [XLEN-1:0] pc
);

    always @(posedge clk or posedge reset) begin
        if (reset) begin
            pc <= {XLEN{1'b0}};
        end 
        else begin
            pc <= next_pc;
        end
    end

endmodule

testbenches/Program_Counter_tb.v
`timescale 1ns/1ps

module ProgramCounter_tb #(
    parameter XLEN = 64
);
    reg clk;
    reg reset;
    reg [XLEN-1:0] next_pc;

    wire [XLEN-1:0] pc;

    ProgramCounter dut (
        .clk(clk),
        .reset(reset),
        .next_pc(next_pc),

        .pc(pc)
    );

    // Generate clock signal (period = 10ns)
    always #5 clk = ~clk;

    initial begin
        $dumpfile("testbenches/results/waveforms/Program_Counter_tb_result.vcd");
        $dumpvars(0, dut);

        $display("==================== Program Counter Test START ====================");

        // Initialize signals
        clk     = 0;
        reset   = 0;
        next_pc = 0;

        // Test 1: Reset the PC
        $display("Reset the PC: ");
		
		next_pc = 64'h0000_0000_0000_0004;
		
		#10;
        $display("Before reset: pc = %h", pc);
		
        reset = 1;
		next_pc = 64'h0000_0000_0000_0008;
		
		#10;
        $display("After reset = 1, pc = %h", pc);

        reset = 0;
        #10;

        // Test 2: Assigning value to next_pc
        $display("\nAssigning value to next_pc: ");
        
		next_pc = 64'hDEAD_BEEF_DEAD_BEEF;
		
        #10;
        $display("pc = %h", pc);

        next_pc = 64'hCAFE_BEBE_CAFE_BEBE;
		
        #10;
        $display("pc = %h", pc);

        // Test 3: Sudden reset
        $display("\nSudden reset:");
		
        #5;
		reset = 1; // Reset signal in the middle of the clock cycle
		#5;
		
        $display("pc = %h", pc);

        $display("\n====================  Program Counter Test END  ====================");
        $stop;
    end

endmodule

testbenches/results/waveforms/Program_Counter_tb_result.vcd
$date
	Thu Dec 25 14:12:35 2025
$end
$version
	Icarus Verilog
$end
$timescale
	1ps
$end
$scope module ProgramCounter_tb $end
$scope module dut $end
$var wire 1 ! clk $end
$var wire 64 " next_pc [63:0] $end
$var wire 1 # reset $end
$var parameter 32 $ XLEN $end
$var reg 64 % pc [63:0] $end
$upscope $end
$upscope $end
$enddefinitions $end
$comment Show the parameter values. $end
$dumpall
b1000000 $
$end
#0
$dumpvars
bx %
0#
b100 "
0!
$end
#5000
b100 %
1!
#10000
b0 %
0!
b1000 "
1#
#15000
1!
#20000
0!
0#
#25000
b1000 %
1!
#30000
0!
b1101111010101101101111101110111111011110101011011011111011101111 "
#35000
b1101111010101101101111101110111111011110101011011011111011101111 %
1!
#40000
0!
b1100101011111110101111101011111011001010111111101011111010111110 "
#45000
b1100101011111110101111101011111011001010111111101011111010111110 %
1!
#50000
0!
#55000
b0 %
1!
1#
