modules/Register_File.v
module RegisterFile # (
    parameter XLEN = 64
)(
    input clk,                      // clock signal
    input [4:0] read_reg1,          // take address of register 1 to read stored value
    input [4:0] read_reg2,          // take address of register 2 to read stored value
    input [4:0] write_reg,          // take address of register to write value
    input [XLEN-1:0] write_data,        // data to write
    input write_enable,             // enabling signal for writing register

    output reg [XLEN-1:0] read_data1,   // data from register 1
    output reg [XLEN-1:0] read_data2    // data from register 2
);

    reg [XLEN-1:0] registers [0:31]; // 64 registers with XLEN bits each

    // Read operation
    always @(*) begin
        read_data1 = (read_reg1 == 5'd0) ? {XLEN{1'b0}} : registers[read_reg1]; // x0 is always 0
        read_data2 = (read_reg2 == 5'd0) ? {XLEN{1'b0}} : registers[read_reg2]; // x0 is always 0
    end

    // Write operation
    always @(posedge clk) begin
        if (write_enable && write_reg != 5'd0) begin
            registers[write_reg] <= write_data; // write to register if not x0
        end
    end

endmodule

testbenches/Register_File_tb.v
`timescale 1ns/1ps

module RegisterFile_tb;
    reg clk;
	reg [4:0] read_reg1;
	reg [4:0] read_reg2;
	reg [4:0] write_reg;
	reg [63:0] write_data;
	reg write_enable;

	wire [63:0] read_data1;
	wire [63:0] read_data2;

    RegisterFile dut (
        .clk(clk),
		.read_reg1(read_reg1),
		.read_reg2(read_reg2),
		.write_reg(write_reg),
		.write_data(write_data),
		.write_enable(write_enable),

		.read_data1(read_data1),
		.read_data2(read_data2)
    );

    // Generate clock signal (period = 10ns)
    always #5 clk = ~clk;

    initial begin
        $dumpfile("testbenches/results/waveforms/Register_File_tb_result.vcd");
        $dumpvars(0, dut);

        $display("==================== Register File Test START ====================");

        // Initialize signals
        clk = 0;
        read_reg1 = 5'b0;
        read_reg2 = 5'b0;
        write_reg = 5'b0;
        write_data = 64'b0;
        write_enable = 0;

        // Test 1: Write and read
        $display("Write and read: ");
		
		write_reg = 5'b00001;
		write_data = 64'hDEAD_BEEF_DEAD_BEEF;
		write_enable = 1;
		
		#10;
        
		read_reg1 = 5'b00001;
		write_enable = 0;
		
		#1;
		
		$display("Value at address %b: %h", read_reg1, read_data1);
		
		write_reg = 5'b00001;
		write_data = 64'hCAFE_BABE_CAFE_BABE;
		write_enable = 1;
		
		#10;
        
		read_reg1 = 5'b00001;
		write_enable = 0;
		
		#1;
		
		$display("Value at address %b: %h", read_reg1, read_data1);
		
		write_reg = 5'b00010;
		write_data = 64'hDEAD_BEEF_DEAD_BEEF;
		write_enable = 1;
		
		#10;
        
		read_reg1 = 5'b00001;
		read_reg2 = 5'b00010;
		write_enable = 0;
		
		#1;
		
		$display("Value at address %b, %b: %h, %h", read_reg1, read_reg2, read_data1, read_data2);
		
		write_reg = 5'b00010;
		write_data = 64'hDEAD_CAFE_DEAD_CAFE;
		write_enable = 1;
		
		#10;
        
		read_reg1 = 5'b00001;
		read_reg2 = 5'b00010;
		write_enable = 0;
		
		#1;
		
		$display("Value at address %b, %b: %h, %h", read_reg1, read_reg2, read_data1, read_data2);
		
		write_reg = 5'b00001;
		write_data = 64'hBEEF_BABE_BEEF_BABE;
		write_enable = 1;
		
		#10;
        
		read_reg1 = 5'b00001;
		read_reg2 = 5'b00010;
		write_enable = 0;
		
		#1;
		
		$display("Value at address %b, %b: %h, %h", read_reg1, read_reg2, read_data1, read_data2);
		
		// Test 2: Zero address
        $display("\nZero address: ");
		
		write_reg = 5'b00000;
		write_data = 64'hDEAD_CAFE_DEAD_CAFE;
		write_enable = 1;
		
		#10;
        
		read_reg1 = 5'b00000;
		read_reg2 = 5'b00010;
		write_enable = 0;
		
		#1;
		
		$display("Value at address %b, %b: %h, %h", read_reg1, read_reg2, read_data1, read_data2);
		
        $display("\n====================  Register File Test END  ====================");
        $stop;
    end

endmodule

testbenches/results/waveforms/Register_File_tb_result.vcd
$date
	Sun Dec 28 17:41:38 2025
$end
$version
	Icarus Verilog
$end
$timescale
	1ps
$end
$scope module RegisterFile_tb $end
$scope module dut $end
$var wire 1 ! clk $end
$var wire 5 " read_reg1 [4:0] $end
$var wire 5 # read_reg2 [4:0] $end
$var wire 64 $ write_data [63:0] $end
$var wire 1 % write_enable $end
$var wire 5 & write_reg [4:0] $end
$var parameter 32 ' XLEN $end
$var reg 64 ( read_data1 [63:0] $end
$var reg 64 ) read_data2 [63:0] $end
$upscope $end
$upscope $end
$enddefinitions $end
$comment Show the parameter values. $end
$dumpall
b1000000 '
$end
#0
$dumpvars
b0 )
b0 (
b1 &
1%
b1101111010101101101111101110111111011110101011011011111011101111 $
b0 #
b0 "
0!
$end
#5000
1!
#10000
b1101111010101101101111101110111111011110101011011011111011101111 (
0!
0%
b1 "
#11000
1%
b1100101011111110101110101011111011001010111111101011101010111110 $
#15000
b1100101011111110101110101011111011001010111111101011101010111110 (
1!
#20000
0!
#21000
0%
#22000
1%
b1101111010101101101111101110111111011110101011011011111011101111 $
b10 &
#25000
1!
#30000
0!
#32000
b1101111010101101101111101110111111011110101011011011111011101111 )
0%
b10 #
#33000
1%
b1101111010101101110010101111111011011110101011011100101011111110 $
#35000
b1101111010101101110010101111111011011110101011011100101011111110 )
1!
#40000
0!
#43000
0%
#44000
1%
b1011111011101111101110101011111010111110111011111011101010111110 $
b1 &
#45000
b1011111011101111101110101011111010111110111011111011101010111110 (
1!
#50000
0!
#54000
0%
#55000
1%
b1101111010101101110010101111111011011110101011011100101011111110 $
b0 &
1!
#60000
0!
#65000
b0 (
1!
0%
b0 "
