modules/Trap_Controller.v
`include "modules/headers/trap.vh"

module TrapController #(
    parameter XLEN = 64
)(
    input wire clk,
    input wire reset,
    input wire [XLEN-1:0] ID_pc,
    input wire [XLEN-1:0] EX_pc,
    input wire [XLEN-1:0] MEM_pc,
    input wire [XLEN-1:0] WB_pc,
    input wire [2:0] trap_status,      // indicates current trap type
    input wire [XLEN-1:0] csr_read_data,

    output reg [XLEN-1:0] trap_target,      // trap handler base address output
    output reg ic_clean,         // instruction cache reset signal for zifencei
    output reg debug_mode,       
    output reg csr_write_enable,
    output reg [11:0] csr_trap_address,
    output reg [XLEN-1:0] csr_trap_write_data,
    output reg trap_done,         // indicates whether PTH(Pre-Trap Hadling) FSM is done or not. if 0 = pc_stall
    output reg misaligned_instruction_flush,        // indicates whether the MISALIGNED INSTRUCTION pth is over and EX_MEM_Register should be flushed or not.
    output reg misaligned_memory_flush,
    output reg pth_done_flush,
    output reg standby_mode
);

// FSM States
localparam  IDLE          = 4'b0000,
            WRITE_MEPC    = 4'b0001,
            WRITE_MCAUSE  = 4'b0010,
            READ_MTVEC    = 4'b0011,
            READ_MEPC     = 4'b0100,
            GOTO_MTVEC    = 4'b0101,
            RETURN_MRET   = 4'b0110,

            MEM_STANDBY   = 4'b0111,
            WB_STANDBY    = 4'b1000,
            RTRE_STANDBY  = 4'b1001,
            ECALL_MEPC_WRITE    = 4'b1010;

// traditional FSM state architecture
reg [3:0] trap_handle_state, next_trap_handle_state;
reg debug_mode_reg; 

// FSM update logic and debug_mode register update
always @(posedge clk or posedge reset) begin
    if (reset) begin
        trap_handle_state <= IDLE;
        debug_mode_reg <= 1'b0; 
    end else begin
        trap_handle_state <= next_trap_handle_state;
        // debug_mode logics
        case (trap_status)
            `TRAP_MRET: begin
                if (trap_handle_state == IDLE) begin
                    debug_mode_reg <= 1'b0;
                end
            end
            `TRAP_EBREAK: begin
                if (trap_handle_state == WRITE_MCAUSE) begin
                    debug_mode_reg <= 1'b1;
                end
            end
            default: begin
                // keep debug_mode_reg
            end
        endcase
    end
end

// debug_mode register
always @(*) begin
    debug_mode = debug_mode_reg;
end

always @(*) begin
    // default outputs
    ic_clean             = 1'b0;
    csr_write_enable     = 1'b0;
    csr_trap_address     = 12'b0;
    csr_trap_write_data  = {XLEN{1'b0}};
    trap_target          = {XLEN{1'b0}};
    trap_done            = 1'b1;
    misaligned_instruction_flush = 1'b0;
    misaligned_memory_flush = 1'b0;
    pth_done_flush       = 1'b0;
    standby_mode = 1'b0;
    // default next state
    next_trap_handle_state = IDLE;

    case (trap_status)
        // traps that doesn't require multiple PTH FSM
        `TRAP_NONE: begin
            next_trap_handle_state = IDLE;
        end
        `TRAP_FENCEI: begin
            ic_clean = 1'b1;
            trap_done = 1'b1;
            next_trap_handle_state = IDLE;
        end

        // ────────── traps that require multiple PTH FSM ──────────
        default: begin
            case (trap_handle_state)
                IDLE: begin 
                    if (trap_status == `TRAP_MRET) begin
                        csr_trap_address = 12'h341; //mepc
                        trap_done = 1'b0;
                        next_trap_handle_state = READ_MEPC;

                    end else if (trap_status == `TRAP_ECALL) begin
                        standby_mode = 1'b1;
                        trap_done = 1'b0;
                        next_trap_handle_state = MEM_STANDBY;

                    end else begin
                        // write current pc value to mepc CSR
                        csr_write_enable = 1'b1;
                        csr_trap_address = 12'h341; //mepc
                        csr_trap_write_data = MEM_pc;
                        trap_done = 1'b0;
                        next_trap_handle_state = WRITE_MEPC;
                    end
                end

                MEM_STANDBY: begin
                    standby_mode = 1'b1;
                    trap_done = 1'b0;
                    next_trap_handle_state = WB_STANDBY;
                end

                WB_STANDBY: begin
                    standby_mode = 1'b1;
                    trap_done = 1'b0;
                    next_trap_handle_state = RTRE_STANDBY;
                end

                RTRE_STANDBY: begin
                    standby_mode = 1'b1;
                    trap_done = 1'b0;
                    next_trap_handle_state = ECALL_MEPC_WRITE;
                end

                ECALL_MEPC_WRITE: begin
                    standby_mode = 1'b0;
                    // write current pc value to mepc CSR
                    csr_write_enable = 1'b1;
                    csr_trap_address = 12'h341; //mepc
                    csr_trap_write_data = EX_pc;
                    trap_done = 1'b0;
                    next_trap_handle_state = WRITE_MEPC;
                end

                WRITE_MEPC: begin 
                    // write mcause code value for each trap type
                    csr_write_enable = 1'b1;
                    csr_trap_address = 12'h342; //mcause
                    if (trap_status == `TRAP_EBREAK)    csr_trap_write_data = 64'd3;
                    else if (trap_status == `TRAP_ECALL)    csr_trap_write_data = 64'd11;
                    else if (trap_status == `TRAP_MISALIGNED_LOAD) csr_trap_write_data = 64'd4;
                    else if (trap_status == `TRAP_MISALIGNED_STORE) csr_trap_write_data = 64'd6;
                    else csr_trap_write_data = 64'd0; // TRAP_MISALIGNED_INSTRUCTION
                    
                    trap_done = 1'b0;
                    next_trap_handle_state = WRITE_MCAUSE;
                end

                WRITE_MCAUSE: begin
                    // Enable debug mode for EBREAK and PTH escape
                    if (trap_status == `TRAP_EBREAK) begin
                        trap_done = 1'b1;
                        next_trap_handle_state = IDLE;
                    end
                    else begin
                        // ECALL, ILLEGAL/MISALIGNED_INSTRUCTION : read mtvec trap handler CSR value
                        csr_write_enable = 1'b0;
                        csr_trap_address = 12'h305; // mtvec
                        trap_target = csr_read_data;
                        trap_done = 1'b0;
                        next_trap_handle_state = READ_MTVEC;
                    end
                end

                READ_MTVEC: begin
                    // keep mtvec value output
                    csr_trap_address = 12'h305; // mtvec
                    trap_target = csr_read_data;
                    if (trap_status == `TRAP_MISALIGNED_INSTRUCTION) begin
                        misaligned_instruction_flush = 1'b1;
                    end else if (trap_status == `TRAP_MISALIGNED_STORE || trap_status == `TRAP_MISALIGNED_LOAD) begin
                        misaligned_memory_flush = 1'b1;
                    end
                    trap_done = 1'b1;
                    pth_done_flush = 1'b1;
                    next_trap_handle_state = GOTO_MTVEC;
                end

                GOTO_MTVEC: begin
                    // keep mtvec value output
                    csr_trap_address = 12'h305; // mtvec
                    trap_target = csr_read_data;
                    if (trap_status == `TRAP_MISALIGNED_INSTRUCTION) begin
                        misaligned_instruction_flush = 1'b1;
                    end else if (trap_status == `TRAP_MISALIGNED_STORE || trap_status == `TRAP_MISALIGNED_LOAD) begin
                        misaligned_memory_flush = 1'b1;
                    end
                    trap_done = 1'b1;
                    pth_done_flush = 1'b1;
                    next_trap_handle_state = IDLE;
                end

                READ_MEPC: begin
                    // keep mepc value output
                    csr_trap_address = 12'h341; // mepc
                    trap_target = ({csr_read_data[XLEN-1:2], 2'b0} + 4);    // For preventing misaligned instruction address
                    trap_done = 1'b0;
                    next_trap_handle_state = RETURN_MRET;
                end

                RETURN_MRET: begin
                    // keep mepc value output
                    csr_trap_address = 12'h341; // mepc
                    trap_target = ({csr_read_data[XLEN-1:2], 2'b0} + 4);    // For preventing misaligned instruction address
                    trap_done = 1'b1;
                    next_trap_handle_state = IDLE;
                end

                default: begin
                    next_trap_handle_state = IDLE;
                end
            endcase
        end
    endcase
end
endmodule

testbenches/Trap_Controller_tb.v
`timescale 1ns/1ps
`include "modules/headers/trap.vh"

module TrapController_tb;
  // Parameters
  parameter XLEN = 64;

  // Signal Declaration
  reg         clk;
  reg         reset;
  reg  [XLEN-1:0] ID_pc;
  reg  [XLEN-1:0] EX_pc;
  reg  [XLEN-1:0] MEM_pc;
  reg  [XLEN-1:0] WB_pc;
  reg  [2:0]  trap_status;
  reg  [XLEN-1:0] csr_read_data;

  wire [XLEN-1:0] trap_target;
  wire        ic_clean;
  wire        debug_mode;
  wire        trap_done;
  wire        csr_write_enable;
  wire [11:0] csr_trap_address;
  wire [XLEN-1:0] csr_trap_write_data;
  wire        misaligned_instruction_flush;
  wire        misaligned_memory_flush;
  wire        pth_done_flush;
  wire        standby_mode;

  // DUT instance
  TrapController #(.XLEN(XLEN)) dut (
    .clk                (clk),
    .reset              (reset),
    .ID_pc              (ID_pc),
    .EX_pc              (EX_pc),
    .MEM_pc             (MEM_pc),
    .WB_pc              (WB_pc),
    .trap_status        (trap_status),
    .csr_read_data      (csr_read_data),

    .trap_target        (trap_target),
    .ic_clean           (ic_clean),
    .debug_mode         (debug_mode),
    .csr_write_enable   (csr_write_enable),
    .csr_trap_address   (csr_trap_address),
    .csr_trap_write_data(csr_trap_write_data),
    .trap_done          (trap_done),
    .misaligned_instruction_flush(misaligned_instruction_flush),
    .misaligned_memory_flush(misaligned_memory_flush),
    .pth_done_flush     (pth_done_flush),
    .standby_mode       (standby_mode)
  );

  // Generate clock signal (period = 10ns)
  initial clk = 0;
  always #5 clk = ~clk;

  // VCD dump
  initial begin
    $dumpfile("testbenches/results/waveforms/Trap_Controller_tb_result.vcd");
    $dumpvars(0, TrapController_tb);
  end

  // Monitor setup :  internal state, CSR Read/Write, output changes
  initial begin
    $display("time | th_state | csr_addr | csr_wd   | csr_we |  trap_tgt  | ic_clean | debug | trap_done | standby | mi_flush | mm_flush | pth_flush");
    $monitor("%4t |  %b   |   %h   | %h |   %b    | %h |     %b    |   %b   |     %b     |    %b    |    %b     |    %b     |     %b",
             $time,
             dut.trap_handle_state,
             csr_trap_address,
             csr_trap_write_data,
             csr_write_enable,
             trap_target,
             ic_clean,
             debug_mode,
             trap_done,
             standby_mode,
             misaligned_instruction_flush,
             misaligned_memory_flush,
             pth_done_flush);
  end

  // Helper task to clear all PC inputs
  task clear_pcs;
    begin
      ID_pc  = {XLEN{1'b0}};
      EX_pc  = {XLEN{1'b0}};
      MEM_pc = {XLEN{1'b0}};
      WB_pc  = {XLEN{1'b0}};
    end
  endtask

  // Helper task to set all PCs to same value (simulating pipeline)
  task set_all_pcs;
    input [XLEN-1:0] pc_value;
    begin
      ID_pc  = pc_value;
      EX_pc  = pc_value;
      MEM_pc = pc_value;
      WB_pc  = pc_value;
    end
  endtask

  // Testbench
  initial begin
    $display("==================== Trap Controller Test START ====================");
    // Initialize signals
    reset          = 1;
    trap_status    = `TRAP_NONE;
    clear_pcs;
    csr_read_data  = 64'h0000_0000;
    #20 reset = 0;

    // -- ECALL Test --
    $display("\n-- ECALL Test --");
    set_all_pcs(64'h0000_1100);
    trap_status  = `TRAP_ECALL;
    // mtvec base address = 1000_AA00
    #25; csr_read_data = 64'h1000_AA00;
    #50;  // Extended for standby states (MEM_STANDBY -> WB_STANDBY -> RTRE_STANDBY -> ECALL_MEPC_WRITE)

    /* expected values
    standby_mode = 1 during MEM_STANDBY, WB_STANDBY, RTRE_STANDBY
    CSR_T.Addr = 12'h341
    CSR_T.WD = EX_pc (0000_1100)
    trap_handle_state = IDLE -> MEM_STANDBY -> WB_STANDBY -> RTRE_STANDBY -> ECALL_MEPC_WRITE -> WRITE_MEPC

    CSR_T.Addr = 12'h342
    CSR_T.WD = 64'd11
    trap_handle_state = WRITE_MEPC -> WRITE_MCAUSE

    trap_target = 1000_AA00
    */

    // -- MRET Test --
    $display("\n-- MRET Test (after ECALL) --");
    // Assumes that mepc already has the value
    trap_status   = `TRAP_MRET;
    csr_read_data = 64'h0000_1100;  // mepc
    #20;
    /* expected values
    CSR_T.Addr = 12'h341
    trap_target = 64'h0000_1104
    debug_mode = 0
    trap_handle_state = IDLE -> READ_MEPC -> RETURN_MRET -> IDLE
    */

    // -- MISALIGNED_INSTRUCTION Test --
    $display("\n-- MISALIGNED_INSTRUCTION Test --");
    MEM_pc        = 64'h0000_1111;
    trap_status   = `TRAP_MISALIGNED_INSTRUCTION;
    // mtvec, go to trap_handler address
    csr_read_data = 64'h1000_AA00; 
    #30;
    // expected trap_target = 1000_AA00
    // mepc = MEM_pc = 0000_1111
    // mcause = 64'd0
    // misaligned_instruction_flush = 1

    // -- MRET Test --
    $display("\n-- MRET Test (after MISALIGNED_INSTRUCTION) --");
    // Assumes that mepc already has the value
    trap_status   = `TRAP_MRET;
    csr_read_data = 64'h0000_1110;  // mepc
    #20;
    /* expected values
    CSR_T.Addr = 12'h341
    trap_target = 64'h0000_1114
    debug_mode = 0
    trap_handle_state = IDLE
    */

    // -- MISALIGNED_STORE Test --
    $display("\n-- MISALIGNED_STORE Test --");
    MEM_pc        = 64'h0000_2220;
    trap_status   = `TRAP_MISALIGNED_STORE;
    csr_read_data = 64'h1000_AA00; 
    #30;
    // expected trap_target = 1000_AA00
    // mepc = MEM_pc = 0000_2220
    // mcause = 64'd6
    // misaligned_memory_flush = 1

    // -- MRET Test --
    $display("\n-- MRET Test (after MISALIGNED_STORE) --");
    trap_status   = `TRAP_MRET;
    csr_read_data = 64'h0000_2220;  // mepc
    #20;

    // -- MISALIGNED_LOAD Test --
    $display("\n-- MISALIGNED_LOAD Test --");
    MEM_pc        = 64'h0000_3330;
    trap_status   = `TRAP_MISALIGNED_LOAD;
    csr_read_data = 64'h1000_AA00; 
    #30;
    // expected trap_target = 1000_AA00
    // mepc = MEM_pc = 0000_3330
    // mcause = 64'd4
    // misaligned_memory_flush = 1

    // -- MRET Test --
    $display("\n-- MRET Test (after MISALIGNED_LOAD) --");
    trap_status   = `TRAP_MRET;
    csr_read_data = 64'h0000_3330;  // mepc
    #20;

    // -- EBREAK Test --
    $display("\n-- EBREAK Test --");
    MEM_pc        = 64'h0000_BBB0;
    trap_status   = `TRAP_EBREAK;
    #20;
    // expected debug_mode = 1
    // mepc = MEM_pc = 0000_BBB0
    // mcause = 64'd3

    // -- MRET Test --
    $display("\n-- MRET Test (after EBREAK) --");
    // Assumes that mepc already has the value
    trap_status   = `TRAP_MRET;
    csr_read_data = 64'h0000_BBB0;  // mepc
    #20;
    /* expected values
    CSR_T.Addr = 12'h341
    trap_target = 64'h0000_BBB4
    debug_mode = 0
    trap_handle_state = IDLE
    */

    // -- FENCE.I Test --
    $display("\n-- FENCE.I Test --");
    trap_status = `TRAP_FENCEI;
    #10;
    // expected ic_clean <= 1'b1

    // -- NONE Test --
    $display("\n-- NONE Test --");
    trap_status = `TRAP_NONE;
    #10;
    $display("\n====================  Trap Controller Test END  ====================");
    $finish;
  end
endmodule

testbenches/results/waveforms/Trap_Controller_tb_result.vcd
$date
	Sun Dec 28 23:25:29 2025
$end
$version
	Icarus Verilog
$end
$timescale
	1ps
$end
$scope module TrapController_tb $end
$var wire 64 ! trap_target [63:0] $end
$var wire 1 " trap_done $end
$var wire 1 # standby_mode $end
$var wire 1 $ pth_done_flush $end
$var wire 1 % misaligned_memory_flush $end
$var wire 1 & misaligned_instruction_flush $end
$var wire 1 ' ic_clean $end
$var wire 1 ( debug_mode $end
$var wire 1 ) csr_write_enable $end
$var wire 64 * csr_trap_write_data [63:0] $end
$var wire 12 + csr_trap_address [11:0] $end
$var parameter 32 , XLEN $end
$var reg 64 - EX_pc [63:0] $end
$var reg 64 . ID_pc [63:0] $end
$var reg 64 / MEM_pc [63:0] $end
$var reg 64 0 WB_pc [63:0] $end
$var reg 1 1 clk $end
$var reg 64 2 csr_read_data [63:0] $end
$var reg 1 3 reset $end
$var reg 3 4 trap_status [2:0] $end
$scope module dut $end
$var wire 64 5 EX_pc [63:0] $end
$var wire 64 6 ID_pc [63:0] $end
$var wire 64 7 MEM_pc [63:0] $end
$var wire 64 8 WB_pc [63:0] $end
$var wire 1 1 clk $end
$var wire 64 9 csr_read_data [63:0] $end
$var wire 1 3 reset $end
$var wire 3 : trap_status [2:0] $end
$var parameter 4 ; ECALL_MEPC_WRITE $end
$var parameter 4 < GOTO_MTVEC $end
$var parameter 4 = IDLE $end
$var parameter 4 > MEM_STANDBY $end
$var parameter 4 ? READ_MEPC $end
$var parameter 4 @ READ_MTVEC $end
$var parameter 4 A RETURN_MRET $end
$var parameter 4 B RTRE_STANDBY $end
$var parameter 4 C WB_STANDBY $end
$var parameter 4 D WRITE_MCAUSE $end
$var parameter 4 E WRITE_MEPC $end
$var parameter 32 F XLEN $end
$var reg 12 G csr_trap_address [11:0] $end
$var reg 64 H csr_trap_write_data [63:0] $end
$var reg 1 ) csr_write_enable $end
$var reg 1 ( debug_mode $end
$var reg 1 I debug_mode_reg $end
$var reg 1 ' ic_clean $end
$var reg 1 & misaligned_instruction_flush $end
$var reg 1 % misaligned_memory_flush $end
$var reg 4 J next_trap_handle_state [3:0] $end
$var reg 1 $ pth_done_flush $end
$var reg 1 # standby_mode $end
$var reg 1 " trap_done $end
$var reg 4 K trap_handle_state [3:0] $end
$var reg 64 L trap_target [63:0] $end
$upscope $end
$scope task clear_pcs $end
$upscope $end
$scope task set_all_pcs $end
$var reg 64 M pc_value [63:0] $end
$upscope $end
$upscope $end
$enddefinitions $end
$comment Show the parameter values. $end
$dumpall
b1000000 F
b1 E
b10 D
b1000 C
b1001 B
b110 A
b11 @
b100 ?
b111 >
b0 =
b101 <
b1010 ;
b1000000 ,
$end
#0
$dumpvars
bx M
b0 L
b0 K
b0 J
0I
b0 H
b0 G
b0 :
b0 9
b0 8
b0 7
b0 6
b0 5
b0 4
13
b0 2
01
b0 0
b0 /
b0 .
b0 -
b0 +
b0 *
0)
0(
0'
0&
0%
0$
0#
1"
b0 !
$end
#5000
11
#10000
01
#15000
11
#20000
b111 J
0"
1#
01
b10 4
b10 :
b1000100000000 0
b1000100000000 8
b1000100000000 /
b1000100000000 7
b1000100000000 -
b1000100000000 5
b1000100000000 .
b1000100000000 6
b1000100000000 M
03
#25000
b1000 J
1#
0"
b111 K
11
#30000
01
#35000
b1001 J
1#
0"
b1000 K
11
#40000
01
#45000
b1001 K
b1010 J
1#
0"
11
b10000000000001010101000000000 2
b10000000000001010101000000000 9
#50000
01
#55000
b1000100000000 *
b1000100000000 H
b1101000001 +
b1101000001 G
1)
b1 J
0#
0"
b1010 K
11
#60000
01
#65000
b10 J
0"
b1011 *
b1011 H
b1101000010 +
b1101000010 G
1)
b1 K
11
#70000
01
#75000
b10000000000001010101000000000 !
b10000000000001010101000000000 L
b11 J
0"
b0 *
b0 H
b1100000101 +
b1100000101 G
0)
b10 K
11
#80000
01
#85000
1$
b101 J
1"
b10000000000001010101000000000 !
b10000000000001010101000000000 L
b1100000101 +
b1100000101 G
b11 K
11
#90000
01
#95000
b101 K
b0 J
1$
b1000100000000 !
b1000100000000 L
b1100000101 +
b1100000101 G
11
b1000100000000 2
b1000100000000 9
b100 4
b100 :
#100000
01
#105000
b100 J
0"
0$
b0 !
b0 L
b1101000001 +
b1101000001 G
b0 K
11
#110000
01
#115000
b1 K
b0 *
b0 H
1)
b10 J
0"
b1101000010 +
b1101000010 G
11
b10000000000001010101000000000 2
b10000000000001010101000000000 9
b11 4
b11 :
b1000100010001 /
b1000100010001 7
#120000
01
#125000
b10000000000001010101000000000 !
b10000000000001010101000000000 L
b11 J
0"
b1100000101 +
b1100000101 G
0)
b10 K
11
#130000
01
#135000
1$
1&
b101 J
1"
b10000000000001010101000000000 !
b10000000000001010101000000000 L
b1100000101 +
b1100000101 G
b11 K
11
#140000
01
#145000
b101 K
b0 J
1$
0&
b1000100010000 !
b1000100010000 L
b1100000101 +
b1100000101 G
11
b1000100010000 2
b1000100010000 9
b100 4
b100 :
#150000
01
#155000
b100 J
0"
0$
b0 !
b0 L
b1101000001 +
b1101000001 G
b0 K
11
#160000
01
#165000
b1 K
b110 *
b110 H
1)
b10 J
0"
b1101000010 +
b1101000010 G
11
b10000000000001010101000000000 2
b10000000000001010101000000000 9
b110 4
b110 :
b10001000100000 /
b10001000100000 7
#170000
01
#175000
b10000000000001010101000000000 !
b10000000000001010101000000000 L
b11 J
0"
b0 *
b0 H
b1100000101 +
b1100000101 G
0)
b10 K
11
#180000
01
#185000
1$
1%
b101 J
1"
b10000000000001010101000000000 !
b10000000000001010101000000000 L
b1100000101 +
b1100000101 G
b11 K
11
#190000
01
#195000
b101 K
b0 J
1$
0%
b10001000100000 !
b10001000100000 L
b1100000101 +
b1100000101 G
11
b10001000100000 2
b10001000100000 9
b100 4
b100 :
#200000
01
#205000
b100 J
0"
0$
b0 !
b0 L
b1101000001 +
b1101000001 G
b0 K
11
#210000
01
#215000
b1 K
b100 *
b100 H
1)
b10 J
0"
b1101000010 +
b1101000010 G
11
b10000000000001010101000000000 2
b10000000000001010101000000000 9
b111 4
b111 :
b11001100110000 /
b11001100110000 7
#220000
01
#225000
b10000000000001010101000000000 !
b10000000000001010101000000000 L
b11 J
0"
b0 *
b0 H
b1100000101 +
b1100000101 G
0)
b10 K
11
#230000
01
#235000
1$
1%
b101 J
1"
b10000000000001010101000000000 !
b10000000000001010101000000000 L
b1100000101 +
b1100000101 G
b11 K
11
#240000
01
#245000
b101 K
b0 J
1$
0%
b11001100110000 !
b11001100110000 L
b1100000101 +
b1100000101 G
11
b11001100110000 2
b11001100110000 9
b100 4
b100 :
#250000
01
#255000
b100 J
0"
0$
b0 !
b0 L
b1101000001 +
b1101000001 G
b0 K
11
#260000
01
#265000
b1 K
b11 *
b11 H
1)
b10 J
0"
b1101000010 +
b1101000010 G
11
b1 4
b1 :
b1011101110110000 /
b1011101110110000 7
#270000
01
#275000
b0 J
1"
b0 *
b0 H
b0 +
b0 G
0)
b10 K
11
#280000
01
#285000
1$
b11 K
b101 J
1"
b1011101110110000 !
b1011101110110000 L
b1100000101 +
b1100000101 G
11
b1011101110110000 2
b1011101110110000 9
b100 4
b100 :
#290000
01
#295000
b0 J
1$
b1011101110110000 !
b1011101110110000 L
b1100000101 +
b1100000101 G
b101 K
11
#300000
01
#305000
b0 K
1'
0$
b0 !
b0 L
b0 +
b0 G
11
b101 4
b101 :
#310000
01
#315000
0'
11
b0 4
b0 :
